Workbook

Sheet 총괄
B2: LG CNS 확약 회전한도(RCF) — 총괄표 (단위: 억원)
B3: 분석 기준 2026.10 · 별도 재무 2026.06.30 · 자금판 2026.07–2028.12 (전 기간 추정) · 공개자료 기반 독립 분석
B5: [1] 제안 개요
B6: 구분 | C6: 금액 | D6: 비율·일자 | E6: 비고
B7: 조달 수단 | C7: 확약 회전한도 | D7: RCF | E7: 기업신용 기반 · 무담보 · 2개 은행 분산 협의
B8: 확약한도 | C8: =가정!$C$61 -> 4500 | D8: =가정!$D$62 -> 0.9 | E8: 회수지연 최대 인출 ÷ 목표 사용률 → 500억 단위 올림
B9: 산정 한도 (검산) | C9: =가정!$C$63 -> 4500 | D9: =IF(C9=C8,"일치","재검토") -> 일치 | E9: 가정 [6] 산식 결과
B10: 약정 기간 | C10: =가정!$C$69 -> 46296 | D10: =가정!$C$70 -> 47026 | E10: 24개월 · 자동 연장 없음 · 만기월 잔액 전액 상환
B11: 인출 금리 | D11: =가정!$D$66 -> 0.042 | E11: 가정 · 은행 견적 전
B12: 미사용 수수료 | D12: =가정!$D$67 -> 0.0025 | E12: 미사용 잔액 기준 연율
B13: 약정 수수료 | C13: =가정!$C$68 -> 6.75 | D13: =가정!$D$68 -> 0.0015 | E13: 신규 협의 한도 기준 일회
B14: 기초 가용유동성 | C14: =가정!$D$11 -> 14044.806 | E14: 별도 현금 + 유동 예치금 (2026.06.30)
B15: 최소 유동성 하한 | C15: =가정!$C$57 -> 7605.7909 | D15: =가정!$C$56 -> 2 | E15: 월 현금영업비용 대용치 × 유지 개월
B17: [2] 시나리오별 결과
B18: 구분 | C18: 기본 | D18: 회수지연 | E18: 복합위기 | F18: 비고
B19: 영업 CF 적용률 (최저) | C19: =MIN(CF_자금판!$E$24:$AH$24) -> 1 | D19: =MIN(CF_자금판!$E$48:$AH$48) -> 0.8 | E19: =MIN(CF_자금판!$E$72:$AH$72) -> 0.6
B20: 추가 회수일수 (최대) | C20: =MAX(CF_자금판!$E$25:$AH$25) -> 0 | D20: =MAX(CF_자금판!$E$49:$AH$49) -> 30 | E20: =MAX(CF_자금판!$E$73:$AH$73) -> 60
B21: GPU 지급 총액 | C21: =-CF_자금판!$C$29 -> 3814 | D21: =-CF_자금판!$C$53 -> 4195.4 | E21: =-CF_자금판!$C$77 -> 4576.8 | F21: 공시 3,814 × 원가 배수
B22: 조달 전 최저 유동성 | C22: =CF_자금판!$D$32 -> 8947.6708 | D22: =CF_자금판!$D$56 -> 3841.3814 | E22: =CF_자금판!$D$80 -> -3294.1409 | F22: 신규 조달 없는 경로
B23: 조달 전 최저 시점 | C23: =INDEX(CF_자금판!$E$6:$AH$6,MATCH(CF_자금판!$D$32,CF_자금판!$E$32:$AH$32,0)) -> 46873 | D23: =INDEX(CF_자금판!$E$6:$AH$6,MATCH(CF_자금판!$D$56,CF_자금판!$E$56:$AH$56,0)) -> 46660 | E23: =INDEX(CF_자금판!$E$6:$AH$6,MATCH(CF_자금판!$D$80,CF_자금판!$E$80:$AH$80,0)) -> 47026
B24: 조달 전 최대 하한 부족 | C24: =MAX(0,-CF_자금판!$D$33) -> 0 | D24: =MAX(0,-CF_자금판!$D$57) -> 3764.4095 | E24: =MAX(0,-CF_자금판!$D$81) -> 10899.932
B25: 최초 인출 시점 | C25: =IF(MAX(CF_자금판!$E$38:$AH$38)<0.001,"—",_xlfn.MINIFS(CF_자금판!$E$6:$AH$6,CF_자금판!$E$38:$AH$38,">0.001")) -> — | D25: =IF(MAX(CF_자금판!$E$62:$AH$62)<0.001,"—",_xlfn.MINIFS(CF_자금판!$E$6:$AH$6,CF_자금판!$E$62:$AH$62,">0.001")) -> 46538 | E25: =IF(MAX(CF_자금판!$E$86:$AH$86)<0.001,"—",_xlfn.MINIFS(CF_자금판!$E$6:$AH$6,CF_자금판!$E$86:$AH$86,">0.001")) -> 46477
B26: 최대 인출잔액 | C26: =MAX(CF_자금판!$E$42:$AH$42) -> 0 | D26: =MAX(CF_자금판!$E$66:$AH$66) -> 3831.8235 | E26: =MAX(CF_자금판!$E$90:$AH$90) -> 4500
B27: 최대 인출 시점 | C27: =IF(MAX(CF_자금판!$E$42:$AH$42)<0.001,"—",INDEX(CF_자금판!$E$6:$AH$6,MATCH(MAX(CF_자금판!$E$42:$AH$42),CF_자금판!$E$42:$AH$42,0))) -> — | D27: =IF(MAX(CF_자금판!$E$66:$AH$66)<0.001,"—",INDEX(CF_자금판!$E$6:$AH$6,MATCH(MAX(CF_자금판!$E$66:$AH$66),CF_자금판!$E$66:$AH$66,0))) -> 46660 | E27: =IF(MAX(CF_자금판!$E$90:$AH$90)<0.001,"—",INDEX(CF_자금판!$E$6:$AH$6,MATCH(MAX(CF_자금판!$E$90:$AH$90),CF_자금판!$E$90:$AH$90,0))) -> 46538
B28: 한도 사용률 (최대) | C28: =MAX(CF_자금판!$E$42:$AH$42)/가정!$C$61 -> 0 | D28: =MAX(CF_자금판!$E$66:$AH$66)/가정!$C$61 -> 0.85151632 | E28: =MAX(CF_자금판!$E$90:$AH$90)/가정!$C$61 -> 1
B29: 전액 상환 시점 | C29: =IF(MAX(CF_자금판!$E$42:$AH$42)<0.001,"—",EOMONTH(_xlfn.MAXIFS(CF_자금판!$E$6:$AH$6,CF_자금판!$E$42:$AH$42,">0.001"),1)) -> — | D29: =IF(MAX(CF_자금판!$E$66:$AH$66)<0.001,"—",EOMONTH(_xlfn.MAXIFS(CF_자금판!$E$6:$AH$6,CF_자금판!$E$66:$AH$66,">0.001"),1)) -> 46934 | E29: =IF(MAX(CF_자금판!$E$90:$AH$90)<0.001,"—",EOMONTH(_xlfn.MAXIFS(CF_자금판!$E$6:$AH$6,CF_자금판!$E$90:$AH$90,">0.001"),1)) -> 47026 | F29: 만기 2028.09 강제 상환 포함
B30: 조달 후 최저 유동성 | C30: =CF_자금판!$D$43 -> 8923.1058 | D30: =CF_자금판!$D$67 -> 7605.7909 | E30: =CF_자금판!$D$91 -> -3593.513
B31: 미해결 하한 부족 | C31: =MAX(0,-CF_자금판!$D$44) -> 0 | D31: =MAX(0,-CF_자금판!$D$68) -> 0 | E31: =MAX(0,-CF_자금판!$D$92) -> 11199.304 | F31: 0 초과 = 한도만으로 해결 불가
B32: 30개월 금융비용 | C32: =CF_자금판!$C$45 -> 29.280822 | D32: =CF_자금판!$C$69 -> 153.23472 | E32: =CF_자금판!$C$93 -> 299.37215
B33: └ 약정 수수료 | C33: =CF_자금판!$C$20 -> 6.75 | D33: =CF_자금판!$C$20 -> 6.75 | E33: =CF_자금판!$C$20 -> 6.75
B34: └ 미사용 수수료 | C34: =CF_자금판!$C$40 -> 22.530822 | D34: =CF_자금판!$C$64 -> 14.685638 | E34: =CF_자금판!$C$88 -> 5.4364338
B35: └ 인출 이자 | C35: =CF_자금판!$C$39 -> 0 | D35: =CF_자금판!$C$63 -> 131.79909 | E35: =CF_자금판!$C$87 -> 287.18572
B36: 기말 가용유동성 (2028.12) | C36: =CF_자금판!$AH$43 -> 9610.5252 | D36: =CF_자금판!$AH$67 -> 8267.2342 | E36: =CF_자금판!$AH$91 -> -3396.6454
B37: 판단 | C37: =IF(C26<0.001,"한도 미인출",IF(C31>0.01,"한도만으로 부족","하한 유지·상환")) -> 한도 미인출 | D37: =IF(D26<0.001,"한도 미인출",IF(D31>0.01,"한도만으로 부족","하한 유지·상환")) -> 하한 유지·상환 | E37: =IF(E26<0.001,"한도 미인출",IF(E31>0.01,"한도만으로 부족","하한 유지·상환")) -> 한도만으로 부족
B39: [3] 조달비용 비교 — 4,500억원 1년 전액 미사용 가정
B40: 구분 | C40: 금액 | D40: 요율 | E40: 산식
B41: 선차입 이자 | C41: =가정!$C$61*가정!$D$66 -> 189 | D41: =가정!$D$66 -> 0.042 | E41: 한도 × 인출 금리
B42: (−) 예금 운용수익 | C42: =-가정!$C$61*가정!$D$71 -> -112.5 | D42: =가정!$D$71 -> 0.025 | E42: 한도 × 운용수익률
B43: (+) 약정 수수료 | C43: =가정!$C$68 -> 6.75 | E43: 선차입도 동일 수수료 가정
B44: 선차입 순비용 | C44: =SUM(C41:C43) -> 83.25
B45: 확약한도 미사용 수수료 | C45: =가정!$C$61*가정!$D$67 -> 11.25 | D45: =가정!$D$67 -> 0.0025 | E45: 한도 × 미사용 수수료
B46: (+) 약정 수수료 | C46: =가정!$C$68 -> 6.75
B47: 확약한도 비용 | C47: =C45+C46 -> 18
B48: 첫해 비용 차이 | C48: =C44-C47 -> 65.25 | E48: 선차입 순비용 − 확약한도 비용
B49: 미사용 수수료 손익분기 | D49: =가정!$D$66-가정!$D$71 -> 0.017 | E49: 이 요율 미만이면 확약한도 유리
B50: 세금·공모 발행비·예금 중도해지 비용 제외 · 실제 인출 시 비교 결과 변동
B52: [4] 투자회수 최소조건 — GPU 3,814억원
B53: 구분 | C53: 금액 | D53: 요율·기간 | E53: 비고
B54: GPU 투자금 | C54: =가정!$C$47 -> 3814
B55: 회수기간 · 요구수익률 | D55: =가정!$C$77 -> 4 | E55: 요구수익률 = 가정 D76
B56: 단순 회수 연평균 순CF | C56: =가정!$C$79 -> 953.5 | E56: 잔존가치 0
B57: NPV = 0 연평균 순CF | C57: =가정!$C$80 -> 1151.5259 | D57: =가정!$D$76 -> 0.08 | E57: 균등 연말 현금흐름
B58: 월 환산 | C58: =가정!$C$81 -> 95.960496 | E58: 고객 수금 − 전력·IDC·운영비 − 세금 기준
B60: [5] 재무 여력 — 회수지연 인출 정점 기준
B61: 구분 | C61: 2026.06 | D61: 인출 정점 | E61: 증감 | F61: 비고
B62: 별도 차입금 (리스 제외) | C62: =공시원문!$F$39 -> 1598.7692 | D62: =공시원문!$F$39-IF(EOMONTH(가정!$D$45,0)<=D27,가정!$C$45,0)-IF(EOMONTH(가정!$D$46,0)<=D27,가정!$C$46,0)+D26 -> 4430.5926 | E62: =D62-C62 -> 2831.8235 | F62: 만기 도래 사채 상환 후 + 최대 인출
B63: 별도 리스부채 | C63: =공시원문!$F$40 -> 4029.8366 | D63: =C63 -> 4029.8366 | E63: =D63-C63 -> 0 | F63: 2026.06 수준 유지 가정
B64: 별도 자본총계 | C64: =공시원문!$F$41 -> 27010.748 | D64: =C64 -> 27010.748 | E64: =D64-C64 -> 0 | F64: 2026.06 수준 유지 가정
B65: 차입금 ÷ 자본 | C65: =C62/C64 -> 0.05919011 | D65: =D62/D64 -> 0.16403072 | E65: =D65-C65 -> 0.10484062
B66: (차입금 + 리스) ÷ 자본 | C66: =(C62+C63)/C64 -> 0.20838392 | D66: =(D62+D63)/D64 -> 0.31322454 | E66: =D66-C66 -> 0.10484062
B67: 인출 정점 = 회수지연 시나리오 최대 인출 시점 · 자본·리스부채는 2026.06 고정 (단순화)
B69: [6] 사용법
B70: ① 가정 시트 노란 셀 수정 (한도·금리·하한 개월·일정)
B71: ② 시나리오별 월별 가정은 CF_자금판 각 블록 상단 3행 (적용률 · 회수일수 · 원가 배수)
B72: ③ 총괄 [2]에서 최대 인출·미해결 부족 확인 → 검증 시트 상태 확인
B73: ④ 2026.07 이후 실적·예금 만기·GPU 지급계약 입수 시 추정치부터 교체

Sheet 가정
B2: LG CNS 자금판 — 가정 (단위: 억원)
B3: 노란 음영·파란 글씨 = 입력값 · 초록 글씨 = 공시원문 연결 · 검정 = 계산 · 성격: 공시 / 가정 / 계산 / 확인필요
B5: [1] 기초 유동성 — 별도 기준
B6: 구분 | C6: 2025.12 | D6: 2026.06 | E6: 증감 | F6: 산식 | G6: 비고
B7: 현금 및 현금성자산 | C7: =공시원문!$F$7 -> 9767.3066 | D7: =공시원문!$F$8 -> 4044.8064 | E7: =D7-C7 -> -5722.5002 | F7: 공시 | G7: 별도 재무상태표
B8: 유동 금융기관예치금 | C8: =공시원문!$F$9 -> 5000 | D8: =공시원문!$F$10 -> 10000 | E8: =D8-C8 -> 5000 | F8: 공시 | G8: 상반기 순증 5,000 · 내부 자금운용 이동
B9: 현금 + 유동 예치금 | C9: =C7+C8 -> 14767.307 | D9: =D7+D8 -> 14044.806 | E9: =D9-C9 -> -722.50018 | F9: 합계 | G9: 실질 감소 규모
B10: (−) 예금 미가용액 | C10: — | D10: 0 | F10: 입력 · 확인필요 | G10: 예치금 만기·질권·해지 제한 확인 후 차감
B11: 기초 가용유동성 | C11: — | D11: =D9-D10 -> 14044.806 | F11: 2026.06 합계 − 미가용액 | G11: CF_자금판 출발점
B13: [2] 2026 상반기 현금 검산
B14: 구분 | C14: 금액 | D14: 요율·시점 | E14: 성격 | F14: 산식 | G14: 비고
B15: 기초 현금 (2025.12) | C15: =C7 -> 9767.3066 | E15: 공시
B16: 영업활동 현금흐름 | C16: =공시원문!$F$11 -> 3449.7158 | E16: 공시
B17: 투자활동 현금흐름 | C17: =공시원문!$F$12 -> -5337.1332 | E17: 공시
B18: └ 예치금 순증 | C18: =-공시원문!$F$15 -> -5000 | E18: 공시 | G18: 현금 → 예치금 이동
B19: └ 기타 투자 | C19: =C17-C18 -> -337.13316 | E19: 계산 | G19: 유·무형자산 취득 등
B20: 재무활동 현금흐름 | C20: =공시원문!$F$13 -> -3839.2587 | E20: 공시
B21: └ 사채 상환 | C21: =-공시원문!$F$16 -> -2300 | E21: 공시
B22: └ 배당금 지급 | C22: =-공시원문!$F$18 -> -1065.7454 | E22: 공시
B23: └ 리스원금 상환 | C23: =-공시원문!$F$17 -> -473.51326 | E23: 공시
B24: 환율 효과 | C24: =공시원문!$F$14 -> 4.17587 | E24: 공시
B25: 기말 현금 (계산) | C25: =C15+C16+C17+C20+C24 -> 4044.8064 | E25: 계산 | F25: 기초 + 영업 + 투자 + 재무 + 환율
B26: 기말 현금 (공시) | C26: =D7 -> 4044.8064 | E26: 공시
B27: 차이 | C27: =C25-C26 -> 0 | E27: 검산 | G27: 0이면 정상
B29: [3] 조정 영업현금흐름 — 자금판 출발점
B30: 구분 | C30: 금액 | D30: 요율·시점 | E30: 성격 | F30: 산식 | G30: 비고
B31: 영업활동 현금흐름 (반기) | C31: =공시원문!$F$11 -> 3449.7158 | E31: 공시
B32: (−) 운전자본 현금유입 | C32: =-공시원문!$F$21 -> -1519.2477 | E32: 공시 | G32: 상반기 회수 효과 반복 배제
B33: (−) 수취이자 | C33: =-공시원문!$F$22 -> -177.02275 | E33: 공시 | G33: 예금 이자 미반영
B34: (−) 수취배당 | C34: =-공시원문!$F$23 -> -57.66878 | E34: 공시
B35: (−) 법인세 환급 | C35: =-공시원문!$F$24 -> -19.90241 | E35: 공시 | G35: 비정기 유입
B36: 조정 영업CF (반기) | C36: =SUM(C31:C35) -> 1675.8742 | E36: 계산 | G36: 지급이자·납부세금은 차감 후 수치
B37: 조정 영업CF (월) | C37: =C36/6 -> 279.31237 | E37: 계산 | F37: 반기 ÷ 6 | G37: GPU 신규 수익 0 (고객계약 미공개)
B39: [4] 고정 유출·확정 일정
B40: 구분 | C40: 금액 | D40: 요율·시점 | E40: 성격 | F40: 산식 | G40: 비고
B41: 기존 CAPEX (월) | C41: =(공시원문!$F$19+공시원문!$F$20)/6 -> 23.046015 | E41: 계산 | F41: 유·무형 현금취득 반기 ÷ 6 | G41: 투자계획 입수 시 월별 실액으로 교체
B42: 리스원금 상환 (월) | C42: =공시원문!$F$17/6 -> 78.918877 | E42: 계산 | F42: 반기 상환액 ÷ 6
B43: 기말배당 (매년) | C43: =공시원문!$F$18 -> 1065.7454 | D43: 4 | E43: 가정 | F43: 2026.04 지급액 반복 | G43: D열 = 지급월
B44: 중간배당 (매년) | C44: =공시원문!$F$32 -> 726.64461 | D44: 9 | E44: 공시·가정 | F44: 2026.09.04 지급예정 · 이후 반복 | G44: D열 = 지급월
B45: 12-3회 사채 만기 | C45: =공시원문!$F$30 -> 1000 | D45: 46521 | E45: 공시 | F45: 만기월 액면 전액 상환
B46: 13-3회 사채 만기 | C46: =공시원문!$F$31 -> 600 | D46: 46822 | E46: 공시 | F46: 만기월 액면 전액 상환
B47: GPU·인프라 장비 취득 | C47: =공시원문!$F$33 -> 3814 | D47: 46568 | E47: 공시 | F47: 지급비중은 CF_자금판 10행 입력 | G47: 취득예정일 · 지급조건 미공개
B48: 2025 별도 매출 | C48: =공시원문!$F$29 -> 54492.71 | E48: 공시
B49: 매출 1일당 금액 | C49: =C48/365 -> 149.2951 | E49: 계산 | F49: 연 매출 ÷ 365 | G49: 회수 1일 지연 시 묶이는 자금
B51: [5] 최소 유동성 하한
B52: 구분 | C52: 금액 | D52: 요율·시점 | E52: 성격 | F52: 산식 | G52: 비고
B53: 매출원가 + 판관비 (반기) | C53: =공시원문!$F$25+공시원문!$F$26 -> 23615.56 | E53: 공시
B54: (−) 감가상각 + 무형상각 | C54: =-(공시원문!$F$27+공시원문!$F$28) -> -798.18775 | E54: 공시
B55: 월 현금영업비용 대용치 | C55: =(C53+C54)/6 -> 3802.8954 | E55: 계산 | F55: (비용 − 상각) ÷ 6
B56: 유지 개월수 | C56: 2 | E56: 가정 | G56: 분석 가정 · 회사 정책 아님. 1개월이면 하한 3,802.9
B57: 최소 유동성 하한 | C57: =C55*C56 -> 7605.7909 | E57: 계산 | F57: 월 현금영업비용 × 유지 개월
B59: [6] 확약 회전한도 (RCF) 조건
B60: 구분 | C60: 금액 | D60: 요율·시점 | E60: 성격 | F60: 산식 | G60: 비고
B61: 확약한도 (목표 총액) | C61: 4500 | E61: 가정 | F61: 회수지연 최대 인출 ÷ 목표 사용률 | G61: 500억 단위 올림
B62: 목표 사용률 | D62: 0.9 | E62: 가정 | G62: 한도 대비 최대 인출 상한
B63: 산정 한도 (검산) | C63: =CEILING(MAX(CF_자금판!$E$66:$AH$66)/D62,500) -> 4500 | E63: 계산 | F63: 회수지연 최대 인출 ÷ 사용률 → 500 올림 | G63: C61과 다르면 한도 재검토
B64: 기존 확약한도 (확인분) | C64: 0 | E64: 확인필요 | G64: 일반 목적·미사용·만기 충족분만 차감
B65: 신규 협의 한도 | C65: =MAX(0,C61-C64) -> 4500 | E65: 계산
B66: 인출 금리 | D66: 0.042 | E66: 가정 | G66: 기준금리 + 가산금리 · 은행 견적 전
B67: 미사용 수수료 | D67: 0.0025 | E67: 가정 | G67: 미사용 잔액 × 연율 × 일수/365
B68: 약정 수수료 (일회) | C68: =C65*D68 -> 6.75 | D68: 0.0015 | E68: 가정 | F68: 신규 협의 한도 × 요율
B69: 약정 개시일 | C69: 46296 | E69: 가정 | G69: 실제 체결일로 수정
B70: 만기일 | C70: 47026 | E70: 가정 | G70: 24개월 · 만기월 잔액 전액 상환 · 자동 연장 없음
B71: 비교용 예금 운용수익률 | D71: 0.025 | E71: 가정 | G71: 총괄 [3] 비용 비교 전용
B73: [7] 투자회수 최소조건 — GPU
B74: 구분 | C74: 금액 | D74: 요율·시점 | E74: 성격 | F74: 산식 | G74: 비고
B75: GPU 투자금 | C75: =C47 -> 3814 | E75: 공시
B76: 요구수익률 (세후) | D76: 0.08 | E76: 가정 | G76: 검토용 · 회사 WACC 아님
B77: 회수기간 | C77: 4 | E77: 가정 | G77: 경제적 회수 시험 · 회계 내용연수 아님
B78: 잔존가치율 | D78: 0 | E78: 가정 | G78: 보수적 0
B79: 단순 회수 연평균 순CF | C79: =(C75-C75*D78)/C77 -> 953.5 | E79: 계산 | F79: (투자금 − 잔존가치) ÷ 기간
B80: NPV = 0 연평균 순CF | C80: =IF(D76=0,C79,(C75-C75*D78/(1+D76)^C77)*D76/(1-(1+D76)^(-C77))) -> 1151.5259 | E80: 계산 | F80: 균등 연말 현금흐름 가정
B81: 월 환산 | C81: =C80/12 -> 95.960496 | E81: 계산 | G81: 고객 수금 − 전력·IDC·운영비 − 세금 기준
B83: [8] 시나리오 정의 — 월별 입력은 CF_자금판 각 블록 상단 3행
B84: 시나리오 | C84: 영업CF 적용률 | D84: 추가 회수일수 | E84: GPU 원가 | F84: 기간·조건
B85: 기본 | C85: 100% | D85: 0일 | E85: +0% | F85: 현금창출 유지
B86: 회수지연 | C86: 80% | D86: 최대 30일 | E86: +10% | F86: CF 80%: 2026.10–2027.12 · 회수일수 2026.10부터 월 3.3일씩 증가, 2027.06–12 30일, 2028.01–06 정상화
B87: 복합위기 | C87: 60% | D87: 최대 60일 | E87: +20% | F87: CF 60%: 2026.10 이후 지속 · 회수일수 2027.06까지 60일로 증가 후 유지
B89: 확률·회사 전망이 아닌 조건 시험 · 원가 스트레스에 환율·부가세 환급시차 포함

Sheet CF_자금판
B2: LG CNS 자금판 — 월별 자금수지 · 3개 시나리오 (단위: 억원)
B3: 2026.07 이후 전 기간 추정 · 월말 기준 · 인출 월초 / 상환 월말 단순화 · 이자 = 실제 일수 / 365 · 노란 음영 = 입력값
B5: 구분 | E5: 2026 | K5: 2027 | W5: 2028
B6: 항목 | C6: 30개월 합계 | D6: 기간 최저 | E6: 46234 | F6: =EOMONTH(E6,1) -> 46265 | G6: =EOMONTH(F6,1) -> 46295 | H6: =EOMONTH(G6,1) -> 46326 | I6: =EOMONTH(H6,1) -> 46356 | J6: =EOMONTH(I6,1) -> 46387 | K6: =EOMONTH(J6,1) -> 46418 | L6: =EOMONTH(K6,1) -> 46446 | M6: =EOMONTH(L6,1) -> 46477 | ... AH6: =EOMONTH(AG6,1) -> 47118
B7: 일수 | E7: =DAY(E$6) -> 31 | F7: =DAY(F$6) -> 31 | G7: =DAY(G$6) -> 30 | H7: =DAY(H$6) -> 31 | I7: =DAY(I$6) -> 30 | J7: =DAY(J$6) -> 31 | K7: =DAY(K$6) -> 31 | L7: =DAY(L$6) -> 28 | ... AH7: =DAY(AH$6) -> 31
B9: [A] 공통 항목
B10: GPU 지급 비중 (입력) | C10: =SUM(E10:AH10) -> 1 | E10: 0 | F10: 0 | G10: 0 | H10: 0.2 | I10: 0 | J10: 0 | K10: 0 | L10: 0 | M10: 0.3 | N10: 0 | O10: 0 | P10: 0.5 | Q10: 0 | R10: 0 | S10: 0 | T10: 0 | U10: 0 | V10: 0 | W10: 0 | X10: 0 | Y10: 0 | Z10: 0 | AA10: 0 | AB10: 0 | AC10: 0 | AD10: 0 | AE10: 0 | AF10: 0 | AG10: 0 | AH10: 0
B11: GPU 지급 (기준 원가) | C11: =SUM(E11:AH11) -> -3814 | E11: =-가정!$C$47*E10 -> 0 | F11: =-가정!$C$47*F10 -> 0 | G11: =-가정!$C$47*G10 -> 0 | H11: =-가정!$C$47*H10 -> -762.8 | I11: =-가정!$C$47*I10 -> 0 | J11: =-가정!$C$47*J10 -> 0 | K11: =-가정!$C$47*K10 -> 0 | L11: =-가정!$C$47*L10 -> 0 | ... AH11: =-가정!$C$47*AH10 -> 0
B12: 기존 CAPEX | C12: =SUM(E12:AH12) -> -691.38045 | E12: =-가정!$C$41 -> -23.046015 | F12: =-가정!$C$41 -> -23.046015 | G12: =-가정!$C$41 -> -23.046015 | H12: =-가정!$C$41 -> -23.046015 | I12: =-가정!$C$41 -> -23.046015 | J12: =-가정!$C$41 -> -23.046015 | K12: =-가정!$C$41 -> -23.046015 | L12: =-가정!$C$41 -> -23.046015 | ... AH12: =-가정!$C$41 -> -23.046015
B13: 리스원금 상환 | C13: =SUM(E13:AH13) -> -2367.5663 | E13: =-가정!$C$42 -> -78.918877 | F13: =-가정!$C$42 -> -78.918877 | G13: =-가정!$C$42 -> -78.918877 | H13: =-가정!$C$42 -> -78.918877 | I13: =-가정!$C$42 -> -78.918877 | J13: =-가정!$C$42 -> -78.918877 | K13: =-가정!$C$42 -> -78.918877 | L13: =-가정!$C$42 -> -78.918877 | ... AH13: =-가정!$C$42 -> -78.918877
B14: 배당금 지급 | C14: =SUM(E14:AH14) -> -4311.4247 | E14: =-(IF(MONTH(E$6)=가정!$D$44,가정!$C$44,0)+IF(MONTH(E$6)=가정!$D$43,가정!$C$43,0)) -> 0 | F14: =-(IF(MONTH(F$6)=가정!$D$44,가정!$C$44,0)+IF(MONTH(F$6)=가정!$D$43,가정!$C$43,0)) -> 0 | G14: =-(IF(MONTH(G$6)=가정!$D$44,가정!$C$44,0)+IF(MONTH(G$6)=가정!$D$43,가정!$C$43,0)) -> -726.64461 | H14: =-(IF(MONTH(H$6)=가정!$D$44,가정!$C$44,0)+IF(MONTH(H$6)=가정!$D$43,가정!$C$43,0)) -> 0 | I14: =-(IF(MONTH(I$6)=가정!$D$44,가정!$C$44,0)+IF(MONTH(I$6)=가정!$D$43,가정!$C$43,0)) -> 0 | J14: =-(IF(MONTH(J$6)=가정!$D$44,가정!$C$44,0)+IF(MONTH(J$6)=가정!$D$43,가정!$C$43,0)) -> 0 | K14: =-(IF(MONTH(K$6)=가정!$D$44,가정!$C$44,0)+IF(MONTH(K$6)=가정!$D$43,가정!$C$43,0)) -> 0 | L14: =-(IF(MONTH(L$6)=가정!$D$44,가정!$C$44,0)+IF(MONTH(L$6)=가정!$D$43,가정!$C$43,0)) -> 0 | ... AH14: =-(IF(MONTH(AH$6)=가정!$D$44,가정!$C$44,0)+IF(MONTH(AH$6)=가정!$D$43,가정!$C$43,0)) -> 0
B15: 기존 사채 만기상환 | C15: =SUM(E15:AH15) -> -1600 | E15: =-(IF(EOMONTH(가정!$D$45,0)=E$6,가정!$C$45,0)+IF(EOMONTH(가정!$D$46,0)=E$6,가정!$C$46,0)) -> 0 | F15: =-(IF(EOMONTH(가정!$D$45,0)=F$6,가정!$C$45,0)+IF(EOMONTH(가정!$D$46,0)=F$6,가정!$C$46,0)) -> 0 | G15: =-(IF(EOMONTH(가정!$D$45,0)=G$6,가정!$C$45,0)+IF(EOMONTH(가정!$D$46,0)=G$6,가정!$C$46,0)) -> 0 | H15: =-(IF(EOMONTH(가정!$D$45,0)=H$6,가정!$C$45,0)+IF(EOMONTH(가정!$D$46,0)=H$6,가정!$C$46,0)) -> 0 | I15: =-(IF(EOMONTH(가정!$D$45,0)=I$6,가정!$C$45,0)+IF(EOMONTH(가정!$D$46,0)=I$6,가정!$C$46,0)) -> 0 | J15: =-(IF(EOMONTH(가정!$D$45,0)=J$6,가정!$C$45,0)+IF(EOMONTH(가정!$D$46,0)=J$6,가정!$C$46,0)) -> 0 | K15: =-(IF(EOMONTH(가정!$D$45,0)=K$6,가정!$C$45,0)+IF(EOMONTH(가정!$D$46,0)=K$6,가정!$C$46,0)) -> 0 | L15: =-(IF(EOMONTH(가정!$D$45,0)=L$6,가정!$C$45,0)+IF(EOMONTH(가정!$D$46,0)=L$6,가정!$C$46,0)) -> 0 | ... AH15: =-(IF(EOMONTH(가정!$D$45,0)=AH$6,가정!$C$45,0)+IF(EOMONTH(가정!$D$46,0)=AH$6,가정!$C$46,0)) -> 0
B16: 추가 승인투자 (입력 · 유출 양수) | C16: =SUM(E16:AH16) -> 0 | E16: 0 | F16: 0 | G16: 0 | H16: 0 | I16: 0 | J16: 0 | K16: 0 | L16: 0 | M16: 0 | N16: 0 | O16: 0 | P16: 0 | Q16: 0 | R16: 0 | S16: 0 | T16: 0 | U16: 0 | V16: 0 | W16: 0 | X16: 0 | Y16: 0 | Z16: 0 | AA16: 0 | AB16: 0 | AC16: 0 | AD16: 0 | AE16: 0 | AF16: 0 | AG16: 0 | AH16: 0
B17: GPU 추가 순현금유입 (입력) | C17: =SUM(E17:AH17) -> 0 | E17: 0 | F17: 0 | G17: 0 | H17: 0 | I17: 0 | J17: 0 | K17: 0 | L17: 0 | M17: 0 | N17: 0 | O17: 0 | P17: 0 | Q17: 0 | R17: 0 | S17: 0 | T17: 0 | U17: 0 | V17: 0 | W17: 0 | X17: 0 | Y17: 0 | Z17: 0 | AA17: 0 | AB17: 0 | AC17: 0 | AD17: 0 | AE17: 0 | AF17: 0 | AG17: 0 | AH17: 0
B18: 공통 현금흐름 계 (GPU 제외) | C18: =SUM(E18:AH18) -> -8970.3714 | E18: =E12+E13+E14+E15-E16+E17 -> -101.96489 | F18: =F12+F13+F14+F15-F16+F17 -> -101.96489 | G18: =G12+G13+G14+G15-G16+G17 -> -828.6095 | H18: =H12+H13+H14+H15-H16+H17 -> -101.96489 | I18: =I12+I13+I14+I15-I16+I17 -> -101.96489 | J18: =J12+J13+J14+J15-J16+J17 -> -101.96489 | K18: =K12+K13+K14+K15-K16+K17 -> -101.96489 | L18: =L12+L13+L14+L15-L16+L17 -> -101.96489 | ... AH18: =AH12+AH13+AH14+AH15-AH16+AH17 -> -101.96489
B19: 활성 확약한도 | E19: =IF(AND(E$6>=EOMONTH(가정!$C$69,0),E$6<=EOMONTH(가정!$C$70,0)),가정!$C$61,0) -> 0 | F19: =IF(AND(F$6>=EOMONTH(가정!$C$69,0),F$6<=EOMONTH(가정!$C$70,0)),가정!$C$61,0) -> 0 | G19: =IF(AND(G$6>=EOMONTH(가정!$C$69,0),G$6<=EOMONTH(가정!$C$70,0)),가정!$C$61,0) -> 0 | H19: =IF(AND(H$6>=EOMONTH(가정!$C$69,0),H$6<=EOMONTH(가정!$C$70,0)),가정!$C$61,0) -> 4500 | I19: =IF(AND(I$6>=EOMONTH(가정!$C$69,0),I$6<=EOMONTH(가정!$C$70,0)),가정!$C$61,0) -> 4500 | J19: =IF(AND(J$6>=EOMONTH(가정!$C$69,0),J$6<=EOMONTH(가정!$C$70,0)),가정!$C$61,0) -> 4500 | K19: =IF(AND(K$6>=EOMONTH(가정!$C$69,0),K$6<=EOMONTH(가정!$C$70,0)),가정!$C$61,0) -> 4500 | L19: =IF(AND(L$6>=EOMONTH(가정!$C$69,0),L$6<=EOMONTH(가정!$C$70,0)),가정!$C$61,0) -> 4500 | ... AH19: =IF(AND(AH$6>=EOMONTH(가정!$C$69,0),AH$6<=EOMONTH(가정!$C$70,0)),가정!$C$61,0) -> 0
B20: 약정 수수료 | C20: =SUM(E20:AH20) -> 6.75 | E20: =IF(E$6=EOMONTH(가정!$C$69,0),가정!$C$68,0) -> 0 | F20: =IF(F$6=EOMONTH(가정!$C$69,0),가정!$C$68,0) -> 0 | G20: =IF(G$6=EOMONTH(가정!$C$69,0),가정!$C$68,0) -> 0 | H20: =IF(H$6=EOMONTH(가정!$C$69,0),가정!$C$68,0) -> 6.75 | I20: =IF(I$6=EOMONTH(가정!$C$69,0),가정!$C$68,0) -> 0 | J20: =IF(J$6=EOMONTH(가정!$C$69,0),가정!$C$68,0) -> 0 | K20: =IF(K$6=EOMONTH(가정!$C$69,0),가정!$C$68,0) -> 0 | L20: =IF(L$6=EOMONTH(가정!$C$69,0),가정!$C$68,0) -> 0 | ... AH20: =IF(AH$6=EOMONTH(가정!$C$69,0),가정!$C$68,0) -> 0
B21: 최소 유동성 하한 | E21: =가정!$C$57 -> 7605.7909 | F21: =가정!$C$57 -> 7605.7909 | G21: =가정!$C$57 -> 7605.7909 | H21: =가정!$C$57 -> 7605.7909 | I21: =가정!$C$57 -> 7605.7909 | J21: =가정!$C$57 -> 7605.7909 | K21: =가정!$C$57 -> 7605.7909 | L21: =가정!$C$57 -> 7605.7909 | ... AH21: =가정!$C$57 -> 7605.7909
B23: [B] 기본 — 현금창출 유지
B24: 영업 CF 적용률 (입력) | E24: 1 | F24: 1 | G24: 1 | H24: 1 | I24: 1 | J24: 1 | K24: 1 | L24: 1 | M24: 1 | N24: 1 | O24: 1 | P24: 1 | Q24: 1 | R24: 1 | S24: 1 | T24: 1 | U24: 1 | V24: 1 | W24: 1 | X24: 1 | Y24: 1 | Z24: 1 | AA24: 1 | AB24: 1 | AC24: 1 | AD24: 1 | AE24: 1 | AF24: 1 | AG24: 1 | AH24: 1
B25: 추가 회수일수 (입력) | E25: 0 | F25: 0 | G25: 0 | H25: 0 | I25: 0 | J25: 0 | K25: 0 | L25: 0 | M25: 0 | N25: 0 | O25: 0 | P25: 0 | Q25: 0 | R25: 0 | S25: 0 | T25: 0 | U25: 0 | V25: 0 | W25: 0 | X25: 0 | Y25: 0 | Z25: 0 | AA25: 0 | AB25: 0 | AC25: 0 | AD25: 0 | AE25: 0 | AF25: 0 | AG25: 0 | AH25: 0
B26: GPU 원가 배수 (입력) | E26: 1 | F26: 1 | G26: 1 | H26: 1 | I26: 1 | J26: 1 | K26: 1 | L26: 1 | M26: 1 | N26: 1 | O26: 1 | P26: 1 | Q26: 1 | R26: 1 | S26: 1 | T26: 1 | U26: 1 | V26: 1 | W26: 1 | X26: 1 | Y26: 1 | Z26: 1 | AA26: 1 | AB26: 1 | AC26: 1 | AD26: 1 | AE26: 1 | AF26: 1 | AG26: 1 | AH26: 1
B27: 조정 영업 CF | C27: =SUM(E27:AH27) -> 8379.371 | E27: =가정!$C$37*E24 -> 279.31237 | F27: =가정!$C$37*F24 -> 279.31237 | G27: =가정!$C$37*G24 -> 279.31237 | H27: =가정!$C$37*H24 -> 279.31237 | I27: =가정!$C$37*I24 -> 279.31237 | J27: =가정!$C$37*J24 -> 279.31237 | K27: =가정!$C$37*K24 -> 279.31237 | L27: =가정!$C$37*L24 -> 279.31237 | ... AH27: =가정!$C$37*AH24 -> 279.31237
B28: 운전자본 증감 (회수 지연) | C28: =SUM(E28:AH28) -> 0 | E28: =(0-E25)*가정!$C$49 -> 0 | F28: =(E25-F25)*가정!$C$49 -> 0 | G28: =(F25-G25)*가정!$C$49 -> 0 | H28: =(G25-H25)*가정!$C$49 -> 0 | I28: =(H25-I25)*가정!$C$49 -> 0 | J28: =(I25-J25)*가정!$C$49 -> 0 | K28: =(J25-K25)*가정!$C$49 -> 0 | L28: =(K25-L25)*가정!$C$49 -> 0 | M28: =(L25-M25)*가정!$C$49 -> 0 | ... AH28: =(AG25-AH25)*가정!$C$49 -> 0
B29: GPU 지급 | C29: =SUM(E29:AH29) -> -3814 | E29: =E$11*E26 -> 0 | F29: =F$11*F26 -> 0 | G29: =G$11*G26 -> 0 | H29: =H$11*H26 -> -762.8 | I29: =I$11*I26 -> 0 | J29: =J$11*J26 -> 0 | K29: =K$11*K26 -> 0 | L29: =L$11*L26 -> 0 | ... AH29: =AH$11*AH26 -> 0
B30: 공통 현금흐름 | C30: =SUM(E30:AH30) -> -8970.3714 | E30: =E$18 -> -101.96489 | F30: =F$18 -> -101.96489 | G30: =G$18 -> -828.6095 | H30: =H$18 -> -101.96489 | I30: =I$18 -> -101.96489 | J30: =J$18 -> -101.96489 | K30: =K$18 -> -101.96489 | L30: =L$18 -> -101.96489 | ... AH30: =AH$18 -> -101.96489
B31: 조달 전 순현금흐름 | C31: =SUM(E31:AH31) -> -4405.0004 | E31: =SUM(E27:E30) -> 177.34748 | F31: =SUM(F27:F30) -> 177.34748 | G31: =SUM(G27:G30) -> -549.29713 | H31: =SUM(H27:H30) -> -585.45252 | I31: =SUM(I27:I30) -> 177.34748 | J31: =SUM(J27:J30) -> 177.34748 | K31: =SUM(K27:K30) -> 177.34748 | L31: =SUM(L27:L30) -> 177.34748 | ... AH31: =SUM(AH27:AH30) -> 177.34748
B32: 조달 전 기말 유동성 | D32: =MIN(E32:AH32) -> 8947.6708 | E32: =가정!$D$11+E31 -> 14222.154 | F32: =E32+F31 -> 14399.501 | G32: =F32+G31 -> 13850.204 | H32: =G32+H31 -> 13264.752 | I32: =H32+I31 -> 13442.099 | J32: =I32+J31 -> 13619.447 | K32: =J32+K31 -> 13796.794 | L32: =K32+L31 -> 13974.142 | M32: =L32+M31 -> 13007.289 | ... AH32: =AG32+AH31 -> 9639.806
B33: 조달 전 하한 대비 | D33: =MIN(E33:AH33) -> 1341.88 | E33: =E32-E$21 -> 6616.3631 | F33: =F32-F$21 -> 6793.7105 | G33: =G32-G$21 -> 6244.4134 | H33: =H32-H$21 -> 5658.9609 | I33: =I32-I$21 -> 5836.3084 | J33: =J32-J$21 -> 6013.6558 | K33: =K32-K$21 -> 6191.0033 | L33: =L32-L$21 -> 6368.3508 | ... AH33: =AH32-AH$21 -> 2034.0152
B34: 기초 가용유동성 | E34: =가정!$D$11 -> 14044.806 | F34: =E43 -> 14222.154 | G34: =F43 -> 14399.501 | H34: =G43 -> 13850.204 | I34: =H43 -> 13257.046 | J34: =I43 -> 13433.469 | K34: =J43 -> 13609.861 | L34: =K43 -> 13786.253 | M34: =L43 -> 13962.738 | ... AH34: =AG43 -> 9433.1778
B35: 인출 전 가용유동성 | E35: =E34+E31 -> 14222.154 | F35: =F34+F31 -> 14399.501 | G35: =G34+G31 -> 13850.204 | H35: =H34+H31 -> 13264.752 | I35: =I34+I31 -> 13434.394 | J35: =J34+J31 -> 13610.817 | K35: =K34+K31 -> 13787.209 | L35: =L34+L31 -> 13963.601 | ... AH35: =AH34+AH31 -> 9610.5252
B36: 기초 인출잔액 | E36: =0 -> 0 | F36: =E42 -> 0 | G36: =F42 -> 0 | H36: =G42 -> 0 | I36: =H42 -> 0 | J36: =I42 -> 0 | K36: =J42 -> 0 | L36: =K42 -> 0 | M36: =L42 -> 0 | ... AH36: =AG42 -> 0
B37: 필요 인출액 (한도 전) | E37: =IF(E$19>0,MAX(0,(E$21-E35+E36*가정!$D$66*E$7/365+MAX(0,E$19-E36)*가정!$D$67*E$7/365+E$20)/(1-가정!$D$66*E$7/365+가정!$D$67*E$7/365)),0) -> 0 | F37: =IF(F$19>0,MAX(0,(F$21-F35+F36*가정!$D$66*F$7/365+MAX(0,F$19-F36)*가정!$D$67*F$7/365+F$20)/(1-가정!$D$66*F$7/365+가정!$D$67*F$7/365)),0) -> 0 | G37: =IF(G$19>0,MAX(0,(G$21-G35+G36*가정!$D$66*G$7/365+MAX(0,G$19-G36)*가정!$D$67*G$7/365+G$20)/(1-가정!$D$66*G$7/365+가정!$D$67*G$7/365)),0) -> 0 | H37: =IF(H$19>0,MAX(0,(H$21-H35+H36*가정!$D$66*H$7/365+MAX(0,H$19-H36)*가정!$D$67*H$7/365+H$20)/(1-가정!$D$66*H$7/365+가정!$D$67*H$7/365)),0) -> 0 | I37: =IF(I$19>0,MAX(0,(I$21-I35+I36*가정!$D$66*I$7/365+MAX(0,I$19-I36)*가정!$D$67*I$7/365+I$20)/(1-가정!$D$66*I$7/365+가정!$D$67*I$7/365)),0) -> 0 | J37: =IF(J$19>0,MAX(0,(J$21-J35+J36*가정!$D$66*J$7/365+MAX(0,J$19-J36)*가정!$D$67*J$7/365+J$20)/(1-가정!$D$66*J$7/365+가정!$D$67*J$7/365)),0) -> 0 | K37: =IF(K$19>0,MAX(0,(K$21-K35+K36*가정!$D$66*K$7/365+MAX(0,K$19-K36)*가정!$D$67*K$7/365+K$20)/(1-가정!$D$66*K$7/365+가정!$D$67*K$7/365)),0) -> 0 | L37: =IF(L$19>0,MAX(0,(L$21-L35+L36*가정!$D$66*L$7/365+MAX(0,L$19-L36)*가정!$D$67*L$7/365+L$20)/(1-가정!$D$66*L$7/365+가정!$D$67*L$7/365)),0) -> 0 | ... AH37: =IF(AH$19>0,MAX(0,(AH$21-AH35+AH36*가정!$D$66*AH$7/365+MAX(0,AH$19-AH36)*가정!$D$67*AH$7/365+AH$20)/(1-가정!$D$66*AH$7/365+가정!$D$67*AH$7/365)),0) -> 0
B38: 인출액 (한도 내) | C38: =SUM(E38:AH38) -> 0 | E38: =MIN(MAX(0,E$19-E36),E37) -> 0 | F38: =MIN(MAX(0,F$19-F36),F37) -> 0 | G38: =MIN(MAX(0,G$19-G36),G37) -> 0 | H38: =MIN(MAX(0,H$19-H36),H37) -> 0 | I38: =MIN(MAX(0,I$19-I36),I37) -> 0 | J38: =MIN(MAX(0,J$19-J36),J37) -> 0 | K38: =MIN(MAX(0,K$19-K36),K37) -> 0 | L38: =MIN(MAX(0,L$19-L36),L37) -> 0 | ... AH38: =MIN(MAX(0,AH$19-AH36),AH37) -> 0
B39: 인출 이자 | C39: =SUM(E39:AH39) -> 0 | E39: =(E36+E38)*가정!$D$66*E$7/365 -> 0 | F39: =(F36+F38)*가정!$D$66*F$7/365 -> 0 | G39: =(G36+G38)*가정!$D$66*G$7/365 -> 0 | H39: =(H36+H38)*가정!$D$66*H$7/365 -> 0 | I39: =(I36+I38)*가정!$D$66*I$7/365 -> 0 | J39: =(J36+J38)*가정!$D$66*J$7/365 -> 0 | K39: =(K36+K38)*가정!$D$66*K$7/365 -> 0 | L39: =(L36+L38)*가정!$D$66*L$7/365 -> 0 | ... AH39: =(AH36+AH38)*가정!$D$66*AH$7/365 -> 0
B40: 미사용 수수료 | C40: =SUM(E40:AH40) -> 22.530822 | E40: =MAX(0,E$19-E36-E38)*가정!$D$67*E$7/365 -> 0 | F40: =MAX(0,F$19-F36-F38)*가정!$D$67*F$7/365 -> 0 | G40: =MAX(0,G$19-G36-G38)*가정!$D$67*G$7/365 -> 0 | H40: =MAX(0,H$19-H36-H38)*가정!$D$67*H$7/365 -> 0.95547945 | I40: =MAX(0,I$19-I36-I38)*가정!$D$67*I$7/365 -> 0.92465753 | J40: =MAX(0,J$19-J36-J38)*가정!$D$67*J$7/365 -> 0.95547945 | K40: =MAX(0,K$19-K36-K38)*가정!$D$67*K$7/365 -> 0.95547945 | L40: =MAX(0,L$19-L36-L38)*가정!$D$67*L$7/365 -> 0.8630137 | ... AH40: =MAX(0,AH$19-AH36-AH38)*가정!$D$67*AH$7/365 -> 0
B41: 상환액 | C41: =SUM(E41:AH41) -> 0 | E41: =IF(E$6=EOMONTH(가정!$C$70,0),E36+E38,MIN(E36+E38,MAX(0,E35+E38-E$20-E39-E40-E$21))) -> 0 | F41: =IF(F$6=EOMONTH(가정!$C$70,0),F36+F38,MIN(F36+F38,MAX(0,F35+F38-F$20-F39-F40-F$21))) -> 0 | G41: =IF(G$6=EOMONTH(가정!$C$70,0),G36+G38,MIN(G36+G38,MAX(0,G35+G38-G$20-G39-G40-G$21))) -> 0 | H41: =IF(H$6=EOMONTH(가정!$C$70,0),H36+H38,MIN(H36+H38,MAX(0,H35+H38-H$20-H39-H40-H$21))) -> 0 | I41: =IF(I$6=EOMONTH(가정!$C$70,0),I36+I38,MIN(I36+I38,MAX(0,I35+I38-I$20-I39-I40-I$21))) -> 0 | J41: =IF(J$6=EOMONTH(가정!$C$70,0),J36+J38,MIN(J36+J38,MAX(0,J35+J38-J$20-J39-J40-J$21))) -> 0 | K41: =IF(K$6=EOMONTH(가정!$C$70,0),K36+K38,MIN(K36+K38,MAX(0,K35+K38-K$20-K39-K40-K$21))) -> 0 | L41: =IF(L$6=EOMONTH(가정!$C$70,0),L36+L38,MIN(L36+L38,MAX(0,L35+L38-L$20-L39-L40-L$21))) -> 0 | ... AH41: =IF(AH$6=EOMONTH(가정!$C$70,0),AH36+AH38,MIN(AH36+AH38,MAX(0,AH35+AH38-AH$20-AH39-AH40-AH$21))) -> 0
B42: 기말 인출잔액 | E42: =E36+E38-E41 -> 0 | F42: =F36+F38-F41 -> 0 | G42: =G36+G38-G41 -> 0 | H42: =H36+H38-H41 -> 0 | I42: =I36+I38-I41 -> 0 | J42: =J36+J38-J41 -> 0 | K42: =K36+K38-K41 -> 0 | L42: =L36+L38-L41 -> 0 | ... AH42: =AH36+AH38-AH41 -> 0
B43: 기말 가용유동성 (조달 후) | D43: =MIN(E43:AH43) -> 8923.1058 | E43: =E35+E38-E$20-E39-E40-E41 -> 14222.154 | F43: =F35+F38-F$20-F39-F40-F41 -> 14399.501 | G43: =G35+G38-G$20-G39-G40-G41 -> 13850.204 | H43: =H35+H38-H$20-H39-H40-H41 -> 13257.046 | I43: =I35+I38-I$20-I39-I40-I41 -> 13433.469 | J43: =J35+J38-J$20-J39-J40-J41 -> 13609.861 | K43: =K35+K38-K$20-K39-K40-K41 -> 13786.253 | L43: =L35+L38-L$20-L39-L40-L41 -> 13962.738 | ... AH43: =AH35+AH38-AH$20-AH39-AH40-AH41 -> 9610.5252
B44: 하한 대비 여유·부족 | D44: =MIN(E44:AH44) -> 1317.3149 | E44: =E43-E$21 -> 6616.3631 | F44: =F43-F$21 -> 6793.7105 | G44: =G43-G$21 -> 6244.4134 | H44: =H43-H$21 -> 5651.2554 | I44: =I43-I$21 -> 5827.6782 | J44: =J43-J$21 -> 6004.0702 | K44: =K43-K$21 -> 6180.4622 | L44: =L43-L$21 -> 6356.9467 | ... AH44: =AH43-AH$21 -> 2004.7344
B45: 금융비용 계 | C45: =SUM(E45:AH45) -> 29.280822 | E45: =E$20+E39+E40 -> 0 | F45: =F$20+F39+F40 -> 0 | G45: =G$20+G39+G40 -> 0 | H45: =H$20+H39+H40 -> 7.7054795 | I45: =I$20+I39+I40 -> 0.92465753 | J45: =J$20+J39+J40 -> 0.95547945 | K45: =K$20+K39+K40 -> 0.95547945 | L45: =L$20+L39+L40 -> 0.8630137 | ... AH45: =AH$20+AH39+AH40 -> 0
B47: [C] 회수지연 — CF 80% · 회수 30일 지연 · GPU 원가 +10%
B48: 영업 CF 적용률 (입력) | E48: 1 | F48: 1 | G48: 1 | H48: 0.8 | I48: 0.8 | J48: 0.8 | K48: 0.8 | L48: 0.8 | M48: 0.8 | N48: 0.8 | O48: 0.8 | P48: 0.8 | Q48: 0.8 | R48: 0.8 | S48: 0.8 | T48: 0.8 | U48: 0.8 | V48: 0.8 | W48: 1 | X48: 1 | Y48: 1 | Z48: 1 | AA48: 1 | AB48: 1 | AC48: 1 | AD48: 1 | AE48: 1 | AF48: 1 | AG48: 1 | AH48: 1
B49: 추가 회수일수 (입력) | E49: 0 | F49: 0 | G49: 0 | H49: 3.333333 | I49: 6.666667 | J49: 10 | K49: 13.333333 | L49: 16.666667 | M49: 20 | N49: 23.333333 | O49: 26.666667 | P49: 30 | Q49: 30 | R49: 30 | S49: 30 | T49: 30 | U49: 30 | V49: 30 | W49: 25 | X49: 20 | Y49: 15 | Z49: 10 | AA49: 5 | AB49: 0 | AC49: 0 | AD49: 0 | AE49: 0 | AF49: 0 | AG49: 0 | AH49: 0
B50: GPU 원가 배수 (입력) | E50: 1.1 | F50: 1.1 | G50: 1.1 | H50: 1.1 | I50: 1.1 | J50: 1.1 | K50: 1.1 | L50: 1.1 | M50: 1.1 | N50: 1.1 | O50: 1.1 | P50: 1.1 | Q50: 1.1 | R50: 1.1 | S50: 1.1 | T50: 1.1 | U50: 1.1 | V50: 1.1 | W50: 1.1 | X50: 1.1 | Y50: 1.1 | Z50: 1.1 | AA50: 1.1 | AB50: 1.1 | AC50: 1.1 | AD50: 1.1 | AE50: 1.1 | AF50: 1.1 | AG50: 1.1 | AH50: 1.1
B51: 조정 영업 CF | C51: =SUM(E51:AH51) -> 7541.4339 | E51: =가정!$C$37*E48 -> 279.31237 | F51: =가정!$C$37*F48 -> 279.31237 | G51: =가정!$C$37*G48 -> 279.31237 | H51: =가정!$C$37*H48 -> 223.44989 | I51: =가정!$C$37*I48 -> 223.44989 | J51: =가정!$C$37*J48 -> 223.44989 | K51: =가정!$C$37*K48 -> 223.44989 | L51: =가정!$C$37*L48 -> 223.44989 | ... AH51: =가정!$C$37*AH48 -> 279.31237
B52: 운전자본 증감 (회수 지연) | C52: =SUM(E52:AH52) -> 0 | E52: =(0-E49)*가정!$C$49 -> 0 | F52: =(E49-F49)*가정!$C$49 -> 0 | G52: =(F49-G49)*가정!$C$49 -> 0 | H52: =(G49-H49)*가정!$C$49 -> -497.65027 | I52: =(H49-I49)*가정!$C$49 -> -497.65042 | J52: =(I49-J49)*가정!$C$49 -> -497.65027 | K52: =(J49-K49)*가정!$C$49 -> -497.65027 | L52: =(K49-L49)*가정!$C$49 -> -497.65042 | M52: =(L49-M49)*가정!$C$49 -> -497.65027 | ... AH52: =(AG49-AH49)*가정!$C$49 -> 0
B53: GPU 지급 | C53: =SUM(E53:AH53) -> -4195.4 | E53: =E$11*E50 -> 0 | F53: =F$11*F50 -> 0 | G53: =G$11*G50 -> 0 | H53: =H$11*H50 -> -839.08 | I53: =I$11*I50 -> 0 | J53: =J$11*J50 -> 0 | K53: =K$11*K50 -> 0 | L53: =L$11*L50 -> 0 | ... AH53: =AH$11*AH50 -> 0
B54: 공통 현금흐름 | C54: =SUM(E54:AH54) -> -8970.3714 | E54: =E$18 -> -101.96489 | F54: =F$18 -> -101.96489 | G54: =G$18 -> -828.6095 | H54: =H$18 -> -101.96489 | I54: =I$18 -> -101.96489 | J54: =J$18 -> -101.96489 | K54: =K$18 -> -101.96489 | L54: =L$18 -> -101.96489 | ... AH54: =AH$18 -> -101.96489
B55: 조달 전 순현금흐름 | C55: =SUM(E55:AH55) -> -5624.3375 | E55: =SUM(E51:E54) -> 177.34748 | F55: =SUM(F51:F54) -> 177.34748 | G55: =SUM(G51:G54) -> -549.29713 | H55: =SUM(H51:H54) -> -1215.2453 | I55: =SUM(I51:I54) -> -376.16542 | J55: =SUM(J51:J54) -> -376.16527 | K55: =SUM(K51:K54) -> -376.16527 | L55: =SUM(L51:L54) -> -376.16542 | ... AH55: =SUM(AH51:AH54) -> 177.34748
B56: 조달 전 기말 유동성 | D56: =MIN(E56:AH56) -> 3841.3814 | E56: =가정!$D$11+E55 -> 14222.154 | F56: =E56+F55 -> 14399.501 | G56: =F56+G55 -> 13850.204 | H56: =G56+H55 -> 12634.959 | I56: =H56+I55 -> 12258.794 | J56: =I56+J55 -> 11882.628 | K56: =J56+K55 -> 11506.463 | L56: =K56+L55 -> 11130.298 | M56: =L56+M55 -> 9495.5124 | ... AH56: =AG56+AH55 -> 8420.4689
B57: 조달 전 하한 대비 | D57: =MIN(E57:AH57) -> -3764.4095 | E57: =E56-E$21 -> 6616.3631 | F57: =F56-F$21 -> 6793.7105 | G57: =G56-G$21 -> 6244.4134 | H57: =H56-H$21 -> 5029.1681 | I57: =I56-I$21 -> 4653.0027 | J57: =J56-J$21 -> 4276.8375 | K57: =K56-K$21 -> 3900.6722 | L57: =L56-L$21 -> 3524.5068 | ... AH57: =AH56-AH$21 -> 814.67809
B58: 기초 가용유동성 | E58: =가정!$D$11 -> 14044.806 | F58: =E67 -> 14222.154 | G58: =F67 -> 14399.501 | H58: =G67 -> 13850.204 | I58: =H67 -> 12627.254 | J58: =I67 -> 12250.163 | K58: =J67 -> 11873.043 | L58: =K67 -> 11495.922 | M58: =L67 -> 11118.894 | ... AH58: =AG67 -> 8089.8867
B59: 인출 전 가용유동성 | E59: =E58+E55 -> 14222.154 | F59: =F58+F55 -> 14399.501 | G59: =G58+G55 -> 13850.204 | H59: =H58+H55 -> 12634.959 | I59: =I58+I55 -> 12251.088 | J59: =J58+J55 -> 11873.998 | K59: =K58+K55 -> 11496.877 | L59: =L58+L55 -> 11119.757 | ... AH59: =AH58+AH55 -> 8267.2342
B60: 기초 인출잔액 | E60: =0 -> 0 | F60: =E66 -> 0 | G60: =F66 -> 0 | H60: =G66 -> 0 | I60: =H66 -> 0 | J60: =I66 -> 0 | K60: =J66 -> 0 | L60: =K66 -> 0 | M60: =L66 -> 0 | ... AH60: =AG66 -> 0
B61: 필요 인출액 (한도 전) | E61: =IF(E$19>0,MAX(0,(E$21-E59+E60*가정!$D$66*E$7/365+MAX(0,E$19-E60)*가정!$D$67*E$7/365+E$20)/(1-가정!$D$66*E$7/365+가정!$D$67*E$7/365)),0) -> 0 | F61: =IF(F$19>0,MAX(0,(F$21-F59+F60*가정!$D$66*F$7/365+MAX(0,F$19-F60)*가정!$D$67*F$7/365+F$20)/(1-가정!$D$66*F$7/365+가정!$D$67*F$7/365)),0) -> 0 | G61: =IF(G$19>0,MAX(0,(G$21-G59+G60*가정!$D$66*G$7/365+MAX(0,G$19-G60)*가정!$D$67*G$7/365+G$20)/(1-가정!$D$66*G$7/365+가정!$D$67*G$7/365)),0) -> 0 | H61: =IF(H$19>0,MAX(0,(H$21-H59+H60*가정!$D$66*H$7/365+MAX(0,H$19-H60)*가정!$D$67*H$7/365+H$20)/(1-가정!$D$66*H$7/365+가정!$D$67*H$7/365)),0) -> 0 | I61: =IF(I$19>0,MAX(0,(I$21-I59+I60*가정!$D$66*I$7/365+MAX(0,I$19-I60)*가정!$D$67*I$7/365+I$20)/(1-가정!$D$66*I$7/365+가정!$D$67*I$7/365)),0) -> 0 | J61: =IF(J$19>0,MAX(0,(J$21-J59+J60*가정!$D$66*J$7/365+MAX(0,J$19-J60)*가정!$D$67*J$7/365+J$20)/(1-가정!$D$66*J$7/365+가정!$D$67*J$7/365)),0) -> 0 | K61: =IF(K$19>0,MAX(0,(K$21-K59+K60*가정!$D$66*K$7/365+MAX(0,K$19-K60)*가정!$D$67*K$7/365+K$20)/(1-가정!$D$66*K$7/365+가정!$D$67*K$7/365)),0) -> 0 | L61: =IF(L$19>0,MAX(0,(L$21-L59+L60*가정!$D$66*L$7/365+MAX(0,L$19-L60)*가정!$D$67*L$7/365+L$20)/(1-가정!$D$66*L$7/365+가정!$D$67*L$7/365)),0) -> 0 | ... AH61: =IF(AH$19>0,MAX(0,(AH$21-AH59+AH60*가정!$D$66*AH$7/365+MAX(0,AH$19-AH60)*가정!$D$67*AH$7/365+AH$20)/(1-가정!$D$66*AH$7/365+가정!$D$67*AH$7/365)),0) -> 0
B62: 인출액 (한도 내) | C62: =SUM(E62:AH62) -> 4197.9787 | E62: =MIN(MAX(0,E$19-E60),E61) -> 0 | F62: =MIN(MAX(0,F$19-F60),F61) -> 0 | G62: =MIN(MAX(0,G$19-G60),G61) -> 0 | H62: =MIN(MAX(0,H$19-H60),H61) -> 0 | I62: =MIN(MAX(0,I$19-I60),I61) -> 0 | J62: =MIN(MAX(0,J$19-J60),J61) -> 0 | K62: =MIN(MAX(0,K$19-K60),K61) -> 0 | L62: =MIN(MAX(0,L$19-L60),L61) -> 0 | ... AH62: =MIN(MAX(0,AH$19-AH60),AH61) -> 0
B63: 인출 이자 | C63: =SUM(E63:AH63) -> 131.79909 | E63: =(E60+E62)*가정!$D$66*E$7/365 -> 0 | F63: =(F60+F62)*가정!$D$66*F$7/365 -> 0 | G63: =(G60+G62)*가정!$D$66*G$7/365 -> 0 | H63: =(H60+H62)*가정!$D$66*H$7/365 -> 0 | I63: =(I60+I62)*가정!$D$66*I$7/365 -> 0 | J63: =(J60+J62)*가정!$D$66*J$7/365 -> 0 | K63: =(K60+K62)*가정!$D$66*K$7/365 -> 0 | L63: =(L60+L62)*가정!$D$66*L$7/365 -> 0 | ... AH63: =(AH60+AH62)*가정!$D$66*AH$7/365 -> 0
B64: 미사용 수수료 | C64: =SUM(E64:AH64) -> 14.685638 | E64: =MAX(0,E$19-E60-E62)*가정!$D$67*E$7/365 -> 0 | F64: =MAX(0,F$19-F60-F62)*가정!$D$67*F$7/365 -> 0 | G64: =MAX(0,G$19-G60-G62)*가정!$D$67*G$7/365 -> 0 | H64: =MAX(0,H$19-H60-H62)*가정!$D$67*H$7/365 -> 0.95547945 | I64: =MAX(0,I$19-I60-I62)*가정!$D$67*I$7/365 -> 0.92465753 | J64: =MAX(0,J$19-J60-J62)*가정!$D$67*J$7/365 -> 0.95547945 | K64: =MAX(0,K$19-K60-K62)*가정!$D$67*K$7/365 -> 0.95547945 | L64: =MAX(0,L$19-L60-L62)*가정!$D$67*L$7/365 -> 0.8630137 | ... AH64: =MAX(0,AH$19-AH60-AH62)*가정!$D$67*AH$7/365 -> 0
B65: 상환액 | C65: =SUM(E65:AH65) -> 4197.9787 | E65: =IF(E$6=EOMONTH(가정!$C$70,0),E60+E62,MIN(E60+E62,MAX(0,E59+E62-E$20-E63-E64-E$21))) -> 0 | F65: =IF(F$6=EOMONTH(가정!$C$70,0),F60+F62,MIN(F60+F62,MAX(0,F59+F62-F$20-F63-F64-F$21))) -> 0 | G65: =IF(G$6=EOMONTH(가정!$C$70,0),G60+G62,MIN(G60+G62,MAX(0,G59+G62-G$20-G63-G64-G$21))) -> 0 | H65: =IF(H$6=EOMONTH(가정!$C$70,0),H60+H62,MIN(H60+H62,MAX(0,H59+H62-H$20-H63-H64-H$21))) -> 0 | I65: =IF(I$6=EOMONTH(가정!$C$70,0),I60+I62,MIN(I60+I62,MAX(0,I59+I62-I$20-I63-I64-I$21))) -> 0 | J65: =IF(J$6=EOMONTH(가정!$C$70,0),J60+J62,MIN(J60+J62,MAX(0,J59+J62-J$20-J63-J64-J$21))) -> 0 | K65: =IF(K$6=EOMONTH(가정!$C$70,0),K60+K62,MIN(K60+K62,MAX(0,K59+K62-K$20-K63-K64-K$21))) -> 0 | L65: =IF(L$6=EOMONTH(가정!$C$70,0),L60+L62,MIN(L60+L62,MAX(0,L59+L62-L$20-L63-L64-L$21))) -> 0 | ... AH65: =IF(AH$6=EOMONTH(가정!$C$70,0),AH60+AH62,MIN(AH60+AH62,MAX(0,AH59+AH62-AH$20-AH63-AH64-AH$21))) -> 0
B66: 기말 인출잔액 | E66: =E60+E62-E65 -> 0 | F66: =F60+F62-F65 -> 0 | G66: =G60+G62-G65 -> 0 | H66: =H60+H62-H65 -> 0 | I66: =I60+I62-I65 -> 0 | J66: =J60+J62-J65 -> 0 | K66: =K60+K62-K65 -> 0 | L66: =L60+L62-L65 -> 0 | ... AH66: =AH60+AH62-AH65 -> 0
B67: 기말 가용유동성 (조달 후) | D67: =MIN(E67:AH67) -> 7605.7909 | E67: =E59+E62-E$20-E63-E64-E65 -> 14222.154 | F67: =F59+F62-F$20-F63-F64-F65 -> 14399.501 | G67: =G59+G62-G$20-G63-G64-G65 -> 13850.204 | H67: =H59+H62-H$20-H63-H64-H65 -> 12627.254 | I67: =I59+I62-I$20-I63-I64-I65 -> 12250.163 | J67: =J59+J62-J$20-J63-J64-J65 -> 11873.043 | K67: =K59+K62-K$20-K63-K64-K65 -> 11495.922 | L67: =L59+L62-L$20-L63-L64-L65 -> 11118.894 | ... AH67: =AH59+AH62-AH$20-AH63-AH64-AH65 -> 8267.2342
B68: 하한 대비 여유·부족 | D68: =MIN(E68:AH68) -> 0 | E68: =E67-E$21 -> 6616.3631 | F68: =F67-F$21 -> 6793.7105 | G68: =G67-G$21 -> 6244.4134 | H68: =H67-H$21 -> 5021.4627 | I68: =I67-I$21 -> 4644.3726 | J68: =J67-J$21 -> 4267.2518 | K68: =K67-K$21 -> 3890.1311 | L68: =L67-L$21 -> 3513.1027 | ... AH68: =AH67-AH$21 -> 661.44337
B69: 금융비용 계 | C69: =SUM(E69:AH69) -> 153.23472 | E69: =E$20+E63+E64 -> 0 | F69: =F$20+F63+F64 -> 0 | G69: =G$20+G63+G64 -> 0 | H69: =H$20+H63+H64 -> 7.7054795 | I69: =I$20+I63+I64 -> 0.92465753 | J69: =J$20+J63+J64 -> 0.95547945 | K69: =K$20+K63+K64 -> 0.95547945 | L69: =L$20+L63+L64 -> 0.8630137 | ... AH69: =AH$20+AH63+AH64 -> 0
B71: [D] 복합위기 — CF 60% 지속 · 회수 60일 지연 지속 · GPU 원가 +20%
B72: 영업 CF 적용률 (입력) | E72: 1 | F72: 1 | G72: 1 | H72: 0.6 | I72: 0.6 | J72: 0.6 | K72: 0.6 | L72: 0.6 | M72: 0.6 | N72: 0.6 | O72: 0.6 | P72: 0.6 | Q72: 0.6 | R72: 0.6 | S72: 0.6 | T72: 0.6 | U72: 0.6 | V72: 0.6 | W72: 0.6 | X72: 0.6 | Y72: 0.6 | Z72: 0.6 | AA72: 0.6 | AB72: 0.6 | AC72: 0.6 | AD72: 0.6 | AE72: 0.6 | AF72: 0.6 | AG72: 0.6 | AH72: 0.6
B73: 추가 회수일수 (입력) | E73: 0 | F73: 0 | G73: 0 | H73: 6.666667 | I73: 13.333333 | J73: 20 | K73: 26.666667 | L73: 33.333333 | M73: 40 | N73: 46.666667 | O73: 53.333333 | P73: 60 | Q73: 60 | R73: 60 | S73: 60 | T73: 60 | U73: 60 | V73: 60 | W73: 60 | X73: 60 | Y73: 60 | Z73: 60 | AA73: 60 | AB73: 60 | AC73: 60 | AD73: 60 | AE73: 60 | AF73: 60 | AG73: 60 | AH73: 60
B74: GPU 원가 배수 (입력) | E74: 1.2 | F74: 1.2 | G74: 1.2 | H74: 1.2 | I74: 1.2 | J74: 1.2 | K74: 1.2 | L74: 1.2 | M74: 1.2 | N74: 1.2 | O74: 1.2 | P74: 1.2 | Q74: 1.2 | R74: 1.2 | S74: 1.2 | T74: 1.2 | U74: 1.2 | V74: 1.2 | W74: 1.2 | X74: 1.2 | Y74: 1.2 | Z74: 1.2 | AA74: 1.2 | AB74: 1.2 | AC74: 1.2 | AD74: 1.2 | AE74: 1.2 | AF74: 1.2 | AG74: 1.2 | AH74: 1.2
B75: 조정 영업 CF | C75: =SUM(E75:AH75) -> 5362.7975 | E75: =가정!$C$37*E72 -> 279.31237 | F75: =가정!$C$37*F72 -> 279.31237 | G75: =가정!$C$37*G72 -> 279.31237 | H75: =가정!$C$37*H72 -> 167.58742 | I75: =가정!$C$37*I72 -> 167.58742 | J75: =가정!$C$37*J72 -> 167.58742 | K75: =가정!$C$37*K72 -> 167.58742 | L75: =가정!$C$37*L72 -> 167.58742 | ... AH75: =가정!$C$37*AH72 -> 167.58742
B76: 운전자본 증감 (회수 지연) | C76: =SUM(E76:AH76) -> -8957.7058 | E76: =(0-E73)*가정!$C$49 -> 0 | F76: =(E73-F73)*가정!$C$49 -> 0 | G76: =(F73-G73)*가정!$C$49 -> 0 | H76: =(G73-H73)*가정!$C$49 -> -995.30069 | I76: =(H73-I73)*가정!$C$49 -> -995.30054 | J76: =(I73-J73)*가정!$C$49 -> -995.30069 | K76: =(J73-K73)*가정!$C$49 -> -995.30069 | L76: =(K73-L73)*가정!$C$49 -> -995.30054 | M76: =(L73-M73)*가정!$C$49 -> -995.30069 | ... AH76: =(AG73-AH73)*가정!$C$49 -> 0
B77: GPU 지급 | C77: =SUM(E77:AH77) -> -4576.8 | E77: =E$11*E74 -> 0 | F77: =F$11*F74 -> 0 | G77: =G$11*G74 -> 0 | H77: =H$11*H74 -> -915.36 | I77: =I$11*I74 -> 0 | J77: =J$11*J74 -> 0 | K77: =K$11*K74 -> 0 | L77: =L$11*L74 -> 0 | ... AH77: =AH$11*AH74 -> 0
B78: 공통 현금흐름 | C78: =SUM(E78:AH78) -> -8970.3714 | E78: =E$18 -> -101.96489 | F78: =F$18 -> -101.96489 | G78: =G$18 -> -828.6095 | H78: =H$18 -> -101.96489 | I78: =I$18 -> -101.96489 | J78: =J$18 -> -101.96489 | K78: =K$18 -> -101.96489 | L78: =L$18 -> -101.96489 | ... AH78: =AH$18 -> -101.96489
B79: 조달 전 순현금흐름 | C79: =SUM(E79:AH79) -> -17142.08 | E79: =SUM(E75:E78) -> 177.34748 | F79: =SUM(F75:F78) -> 177.34748 | G79: =SUM(G75:G78) -> -549.29713 | H79: =SUM(H75:H78) -> -1845.0382 | I79: =SUM(I75:I78) -> -929.67801 | J79: =SUM(J75:J78) -> -929.67816 | K79: =SUM(K75:K78) -> -929.67816 | L79: =SUM(L75:L78) -> -929.67801 | ... AH79: =SUM(AH75:AH78) -> 65.622529
B80: 조달 전 기말 유동성 | D80: =MIN(E80:AH80) -> -3294.1409 | E80: =가정!$D$11+E79 -> 14222.154 | F80: =E80+F79 -> 14399.501 | G80: =F80+G79 -> 13850.204 | H80: =G80+H79 -> 12005.166 | I80: =H80+I79 -> 11075.488 | J80: =I80+J79 -> 10145.81 | K80: =J80+K79 -> 9216.1318 | L80: =K80+L79 -> 8286.4538 | M80: =L80+M79 -> 5983.7356 | ... AH80: =AG80+AH79 -> -3097.2733
B81: 조달 전 하한 대비 | D81: =MIN(E81:AH81) -> -10899.932 | E81: =E80-E$21 -> 6616.3631 | F81: =F80-F$21 -> 6793.7105 | G81: =G80-G$21 -> 6244.4134 | H81: =H80-H$21 -> 4399.3752 | I81: =I80-I$21 -> 3469.6972 | J81: =J80-J$21 -> 2540.0191 | K81: =K80-K$21 -> 1610.3409 | L81: =L80-L$21 -> 680.66291 | ... AH81: =AH80-AH$21 -> -10703.064
B82: 기초 가용유동성 | E82: =가정!$D$11 -> 14044.806 | F82: =E91 -> 14222.154 | G82: =F91 -> 14399.501 | H82: =G91 -> 13850.204 | I82: =H91 -> 11997.461 | J82: =I91 -> 11066.858 | K82: =J91 -> 10136.224 | L82: =K91 -> 9205.5907 | M82: =L91 -> 8275.0497 | ... AH82: =AG91 -> -3462.268
B83: 인출 전 가용유동성 | E83: =E82+E79 -> 14222.154 | F83: =F82+F79 -> 14399.501 | G83: =G82+G79 -> 13850.204 | H83: =H82+H79 -> 12005.166 | I83: =I82+I79 -> 11067.783 | J83: =J82+J79 -> 10137.18 | K83: =K82+K79 -> 9206.5462 | L83: =L82+L79 -> 8275.9127 | ... AH83: =AH82+AH79 -> -3396.6454
B84: 기초 인출잔액 | E84: =0 -> 0 | F84: =E90 -> 0 | G84: =F90 -> 0 | H84: =G90 -> 0 | I84: =H90 -> 0 | J84: =I90 -> 0 | K84: =J90 -> 0 | L84: =K90 -> 0 | M84: =L90 -> 0 | ... AH84: =AG90 -> 0
B85: 필요 인출액 (한도 전) | E85: =IF(E$19>0,MAX(0,(E$21-E83+E84*가정!$D$66*E$7/365+MAX(0,E$19-E84)*가정!$D$67*E$7/365+E$20)/(1-가정!$D$66*E$7/365+가정!$D$67*E$7/365)),0) -> 0 | F85: =IF(F$19>0,MAX(0,(F$21-F83+F84*가정!$D$66*F$7/365+MAX(0,F$19-F84)*가정!$D$67*F$7/365+F$20)/(1-가정!$D$66*F$7/365+가정!$D$67*F$7/365)),0) -> 0 | G85: =IF(G$19>0,MAX(0,(G$21-G83+G84*가정!$D$66*G$7/365+MAX(0,G$19-G84)*가정!$D$67*G$7/365+G$20)/(1-가정!$D$66*G$7/365+가정!$D$67*G$7/365)),0) -> 0 | H85: =IF(H$19>0,MAX(0,(H$21-H83+H84*가정!$D$66*H$7/365+MAX(0,H$19-H84)*가정!$D$67*H$7/365+H$20)/(1-가정!$D$66*H$7/365+가정!$D$67*H$7/365)),0) -> 0 | I85: =IF(I$19>0,MAX(0,(I$21-I83+I84*가정!$D$66*I$7/365+MAX(0,I$19-I84)*가정!$D$67*I$7/365+I$20)/(1-가정!$D$66*I$7/365+가정!$D$67*I$7/365)),0) -> 0 | J85: =IF(J$19>0,MAX(0,(J$21-J83+J84*가정!$D$66*J$7/365+MAX(0,J$19-J84)*가정!$D$67*J$7/365+J$20)/(1-가정!$D$66*J$7/365+가정!$D$67*J$7/365)),0) -> 0 | K85: =IF(K$19>0,MAX(0,(K$21-K83+K84*가정!$D$66*K$7/365+MAX(0,K$19-K84)*가정!$D$67*K$7/365+K$20)/(1-가정!$D$66*K$7/365+가정!$D$67*K$7/365)),0) -> 0 | L85: =IF(L$19>0,MAX(0,(L$21-L83+L84*가정!$D$66*L$7/365+MAX(0,L$19-L84)*가정!$D$67*L$7/365+L$20)/(1-가정!$D$66*L$7/365+가정!$D$67*L$7/365)),0) -> 0 | ... AH85: =IF(AH$19>0,MAX(0,(AH$21-AH83+AH84*가정!$D$66*AH$7/365+MAX(0,AH$19-AH84)*가정!$D$67*AH$7/365+AH$20)/(1-가정!$D$66*AH$7/365+가정!$D$67*AH$7/365)),0) -> 0
B86: 인출액 (한도 내) | C86: =SUM(E86:AH86) -> 4500 | E86: =MIN(MAX(0,E$19-E84),E85) -> 0 | F86: =MIN(MAX(0,F$19-F84),F85) -> 0 | G86: =MIN(MAX(0,G$19-G84),G85) -> 0 | H86: =MIN(MAX(0,H$19-H84),H85) -> 0 | I86: =MIN(MAX(0,I$19-I84),I85) -> 0 | J86: =MIN(MAX(0,J$19-J84),J85) -> 0 | K86: =MIN(MAX(0,K$19-K84),K85) -> 0 | L86: =MIN(MAX(0,L$19-L84),L85) -> 0 | ... AH86: =MIN(MAX(0,AH$19-AH84),AH85) -> 0
B87: 인출 이자 | C87: =SUM(E87:AH87) -> 287.18572 | E87: =(E84+E86)*가정!$D$66*E$7/365 -> 0 | F87: =(F84+F86)*가정!$D$66*F$7/365 -> 0 | G87: =(G84+G86)*가정!$D$66*G$7/365 -> 0 | H87: =(H84+H86)*가정!$D$66*H$7/365 -> 0 | I87: =(I84+I86)*가정!$D$66*I$7/365 -> 0 | J87: =(J84+J86)*가정!$D$66*J$7/365 -> 0 | K87: =(K84+K86)*가정!$D$66*K$7/365 -> 0 | L87: =(L84+L86)*가정!$D$66*L$7/365 -> 0 | ... AH87: =(AH84+AH86)*가정!$D$66*AH$7/365 -> 0
B88: 미사용 수수료 | C88: =SUM(E88:AH88) -> 5.4364338 | E88: =MAX(0,E$19-E84-E86)*가정!$D$67*E$7/365 -> 0 | F88: =MAX(0,F$19-F84-F86)*가정!$D$67*F$7/365 -> 0 | G88: =MAX(0,G$19-G84-G86)*가정!$D$67*G$7/365 -> 0 | H88: =MAX(0,H$19-H84-H86)*가정!$D$67*H$7/365 -> 0.95547945 | I88: =MAX(0,I$19-I84-I86)*가정!$D$67*I$7/365 -> 0.92465753 | J88: =MAX(0,J$19-J84-J86)*가정!$D$67*J$7/365 -> 0.95547945 | K88: =MAX(0,K$19-K84-K86)*가정!$D$67*K$7/365 -> 0.95547945 | L88: =MAX(0,L$19-L84-L86)*가정!$D$67*L$7/365 -> 0.8630137 | ... AH88: =MAX(0,AH$19-AH84-AH86)*가정!$D$67*AH$7/365 -> 0
B89: 상환액 | C89: =SUM(E89:AH89) -> 4500 | E89: =IF(E$6=EOMONTH(가정!$C$70,0),E84+E86,MIN(E84+E86,MAX(0,E83+E86-E$20-E87-E88-E$21))) -> 0 | F89: =IF(F$6=EOMONTH(가정!$C$70,0),F84+F86,MIN(F84+F86,MAX(0,F83+F86-F$20-F87-F88-F$21))) -> 0 | G89: =IF(G$6=EOMONTH(가정!$C$70,0),G84+G86,MIN(G84+G86,MAX(0,G83+G86-G$20-G87-G88-G$21))) -> 0 | H89: =IF(H$6=EOMONTH(가정!$C$70,0),H84+H86,MIN(H84+H86,MAX(0,H83+H86-H$20-H87-H88-H$21))) -> 0 | I89: =IF(I$6=EOMONTH(가정!$C$70,0),I84+I86,MIN(I84+I86,MAX(0,I83+I86-I$20-I87-I88-I$21))) -> 0 | J89: =IF(J$6=EOMONTH(가정!$C$70,0),J84+J86,MIN(J84+J86,MAX(0,J83+J86-J$20-J87-J88-J$21))) -> 0 | K89: =IF(K$6=EOMONTH(가정!$C$70,0),K84+K86,MIN(K84+K86,MAX(0,K83+K86-K$20-K87-K88-K$21))) -> 0 | L89: =IF(L$6=EOMONTH(가정!$C$70,0),L84+L86,MIN(L84+L86,MAX(0,L83+L86-L$20-L87-L88-L$21))) -> 0 | ... AH89: =IF(AH$6=EOMONTH(가정!$C$70,0),AH84+AH86,MIN(AH84+AH86,MAX(0,AH83+AH86-AH$20-AH87-AH88-AH$21))) -> 0
B90: 기말 인출잔액 | E90: =E84+E86-E89 -> 0 | F90: =F84+F86-F89 -> 0 | G90: =G84+G86-G89 -> 0 | H90: =H84+H86-H89 -> 0 | I90: =I84+I86-I89 -> 0 | J90: =J84+J86-J89 -> 0 | K90: =K84+K86-K89 -> 0 | L90: =L84+L86-L89 -> 0 | ... AH90: =AH84+AH86-AH89 -> 0
B91: 기말 가용유동성 (조달 후) | D91: =MIN(E91:AH91) -> -3593.513 | E91: =E83+E86-E$20-E87-E88-E89 -> 14222.154 | F91: =F83+F86-F$20-F87-F88-F89 -> 14399.501 | G91: =G83+G86-G$20-G87-G88-G89 -> 13850.204 | H91: =H83+H86-H$20-H87-H88-H89 -> 11997.461 | I91: =I83+I86-I$20-I87-I88-I89 -> 11066.858 | J91: =J83+J86-J$20-J87-J88-J89 -> 10136.224 | K91: =K83+K86-K$20-K87-K88-K89 -> 9205.5907 | L91: =L83+L86-L$20-L87-L88-L89 -> 8275.0497 | ... AH91: =AH83+AH86-AH$20-AH87-AH88-AH89 -> -3396.6454
B92: 하한 대비 여유·부족 | D92: =MIN(E92:AH92) -> -11199.304 | E92: =E91-E$21 -> 6616.3631 | F92: =F91-F$21 -> 6793.7105 | G92: =G91-G$21 -> 6244.4134 | H92: =H91-H$21 -> 4391.6698 | I92: =I91-I$21 -> 3461.0671 | J92: =J91-J$21 -> 2530.4335 | K92: =K91-K$21 -> 1599.7998 | L92: =L91-L$21 -> 669.2588 | ... AH92: =AH91-AH$21 -> -11002.436
B93: 금융비용 계 | C93: =SUM(E93:AH93) -> 299.37215 | E93: =E$20+E87+E88 -> 0 | F93: =F$20+F87+F88 -> 0 | G93: =G$20+G87+G88 -> 0 | H93: =H$20+H87+H88 -> 7.7054795 | I93: =I$20+I87+I88 -> 0.92465753 | J93: =J$20+J87+J88 -> 0.95547945 | K93: =K$20+K87+K88 -> 0.95547945 | L93: =L$20+L87+L88 -> 0.8630137 | ... AH93: =AH$20+AH87+AH88 -> 0
B96: 계산 순서: 월말 부족액을 월초 인출로 간주 · 인출잔액 이자는 실제 일수/365로 한 달 전액 부과 · 미사용 수수료는 인출 직후 잔액 기준 · 상환은 월말
B97: 필요 인출액 = (하한 − 인출 전 가용 + 기존잔액 이자 + 미사용 수수료 + 약정 수수료) ÷ (1 − 금리×일수/365 + 수수료율×일수/365) → 순환참조 없이 당월 비용 반영
B98: 하한 부족·현금 마이너스 = 해당 가정 조합의 미해결 자금부족 경보 · 만기월은 연장 없이 전액 상환 · 실행 전 13주 일별 자금계획으로 보완

Sheet 연도별요약
B2: LG CNS 자금판 — 연도별 요약 (단위: 억원)
B3: 2026년은 7–12월 · 합계는 30개월 · 기말·최저는 조달 후 기준
C5: 2026 | D5: 2027 | E5: 2028
B7: [1] 기본
B8: 항목 | C8: 2026H2 | D8: 2027 | E8: 2028 | F8: 합계 | G8: 비고
B9: 조정 영업 CF | C9: =SUMPRODUCT((YEAR(CF_자금판!$E$6:$AH$6)=C$5)*CF_자금판!$E$27:$AH$27) -> 1675.8742 | D9: =SUMPRODUCT((YEAR(CF_자금판!$E$6:$AH$6)=D$5)*CF_자금판!$E$27:$AH$27) -> 3351.7484 | E9: =SUMPRODUCT((YEAR(CF_자금판!$E$6:$AH$6)=E$5)*CF_자금판!$E$27:$AH$27) -> 3351.7484 | F9: =SUM(C9:E9) -> 8379.371
B10: 운전자본 증감 | C10: =SUMPRODUCT((YEAR(CF_자금판!$E$6:$AH$6)=C$5)*CF_자금판!$E$28:$AH$28) -> 0 | D10: =SUMPRODUCT((YEAR(CF_자금판!$E$6:$AH$6)=D$5)*CF_자금판!$E$28:$AH$28) -> 0 | E10: =SUMPRODUCT((YEAR(CF_자금판!$E$6:$AH$6)=E$5)*CF_자금판!$E$28:$AH$28) -> 0 | F10: =SUM(C10:E10) -> 0 | G10: 회수 지연분 · 정상화 시 환입
B11: GPU 지급 | C11: =SUMPRODUCT((YEAR(CF_자금판!$E$6:$AH$6)=C$5)*CF_자금판!$E$29:$AH$29) -> -762.8 | D11: =SUMPRODUCT((YEAR(CF_자금판!$E$6:$AH$6)=D$5)*CF_자금판!$E$29:$AH$29) -> -3051.2 | E11: =SUMPRODUCT((YEAR(CF_자금판!$E$6:$AH$6)=E$5)*CF_자금판!$E$29:$AH$29) -> 0 | F11: =SUM(C11:E11) -> -3814
B12: 기존 CAPEX · 리스원금 | C12: =(SUMPRODUCT((YEAR(CF_자금판!$E$6:$AH$6)=C$5)*CF_자금판!$E$12:$AH$12)+SUMPRODUCT((YEAR(CF_자금판!$E$6:$AH$6)=C$5)*CF_자금판!$E$13:$AH$13)) -> -611.78935 | D12: =(SUMPRODUCT((YEAR(CF_자금판!$E$6:$AH$6)=D$5)*CF_자금판!$E$12:$AH$12)+SUMPRODUCT((YEAR(CF_자금판!$E$6:$AH$6)=D$5)*CF_자금판!$E$13:$AH$13)) -> -1223.5787 | E12: =(SUMPRODUCT((YEAR(CF_자금판!$E$6:$AH$6)=E$5)*CF_자금판!$E$12:$AH$12)+SUMPRODUCT((YEAR(CF_자금판!$E$6:$AH$6)=E$5)*CF_자금판!$E$13:$AH$13)) -> -1223.5787 | F12: =SUM(C12:E12) -> -3058.9468
B13: 배당금 | C13: =SUMPRODUCT((YEAR(CF_자금판!$E$6:$AH$6)=C$5)*CF_자금판!$E$14:$AH$14) -> -726.64461 | D13: =SUMPRODUCT((YEAR(CF_자금판!$E$6:$AH$6)=D$5)*CF_자금판!$E$14:$AH$14) -> -1792.39 | E13: =SUMPRODUCT((YEAR(CF_자금판!$E$6:$AH$6)=E$5)*CF_자금판!$E$14:$AH$14) -> -1792.39 | F13: =SUM(C13:E13) -> -4311.4247 | G13: 4월 기말 · 9월 중간
B14: 기존 사채 상환 | C14: =SUMPRODUCT((YEAR(CF_자금판!$E$6:$AH$6)=C$5)*CF_자금판!$E$15:$AH$15) -> 0 | D14: =SUMPRODUCT((YEAR(CF_자금판!$E$6:$AH$6)=D$5)*CF_자금판!$E$15:$AH$15) -> -1000 | E14: =SUMPRODUCT((YEAR(CF_자금판!$E$6:$AH$6)=E$5)*CF_자금판!$E$15:$AH$15) -> -600 | F14: =SUM(C14:E14) -> -1600
B15: 추가투자 · GPU 추가CF | C15: =SUMPRODUCT((YEAR(CF_자금판!$E$6:$AH$6)=C$5)*CF_자금판!$E$17:$AH$17)-SUMPRODUCT((YEAR(CF_자금판!$E$6:$AH$6)=C$5)*CF_자금판!$E$16:$AH$16) -> 0 | D15: =SUMPRODUCT((YEAR(CF_자금판!$E$6:$AH$6)=D$5)*CF_자금판!$E$17:$AH$17)-SUMPRODUCT((YEAR(CF_자금판!$E$6:$AH$6)=D$5)*CF_자금판!$E$16:$AH$16) -> 0 | E15: =SUMPRODUCT((YEAR(CF_자금판!$E$6:$AH$6)=E$5)*CF_자금판!$E$17:$AH$17)-SUMPRODUCT((YEAR(CF_자금판!$E$6:$AH$6)=E$5)*CF_자금판!$E$16:$AH$16) -> 0 | F15: =SUM(C15:E15) -> 0 | G15: 기본 0
B16: 조달 전 순현금흐름 | C16: =SUMPRODUCT((YEAR(CF_자금판!$E$6:$AH$6)=C$5)*CF_자금판!$E$31:$AH$31) -> -425.35975 | D16: =SUMPRODUCT((YEAR(CF_자금판!$E$6:$AH$6)=D$5)*CF_자금판!$E$31:$AH$31) -> -3715.4203 | E16: =SUMPRODUCT((YEAR(CF_자금판!$E$6:$AH$6)=E$5)*CF_자금판!$E$31:$AH$31) -> -264.22032 | F16: =SUM(C16:E16) -> -4405.0004
B17: 신규 인출 | C17: =SUMPRODUCT((YEAR(CF_자금판!$E$6:$AH$6)=C$5)*CF_자금판!$E$38:$AH$38) -> 0 | D17: =SUMPRODUCT((YEAR(CF_자금판!$E$6:$AH$6)=D$5)*CF_자금판!$E$38:$AH$38) -> 0 | E17: =SUMPRODUCT((YEAR(CF_자금판!$E$6:$AH$6)=E$5)*CF_자금판!$E$38:$AH$38) -> 0 | F17: =SUM(C17:E17) -> 0
B18: 차입 상환 | C18: =-(SUMPRODUCT((YEAR(CF_자금판!$E$6:$AH$6)=C$5)*CF_자금판!$E$41:$AH$41)) -> 0 | D18: =-(SUMPRODUCT((YEAR(CF_자금판!$E$6:$AH$6)=D$5)*CF_자금판!$E$41:$AH$41)) -> 0 | E18: =-(SUMPRODUCT((YEAR(CF_자금판!$E$6:$AH$6)=E$5)*CF_자금판!$E$41:$AH$41)) -> 0 | F18: =SUM(C18:E18) -> 0
B19: 금융비용 | C19: =-(SUMPRODUCT((YEAR(CF_자금판!$E$6:$AH$6)=C$5)*CF_자금판!$E$45:$AH$45)) -> -9.5856164 | D19: =-(SUMPRODUCT((YEAR(CF_자금판!$E$6:$AH$6)=D$5)*CF_자금판!$E$45:$AH$45)) -> -11.25 | E19: =-(SUMPRODUCT((YEAR(CF_자금판!$E$6:$AH$6)=E$5)*CF_자금판!$E$45:$AH$45)) -> -8.4452055 | F19: =SUM(C19:E19) -> -29.280822 | G19: 약정·미사용 수수료 + 이자
B20: 기말 가용유동성 | C20: =INDEX(CF_자금판!$E$43:$AH$43,MATCH(DATE(C$5,12,31),CF_자금판!$E$6:$AH$6,0)) -> 13609.861 | D20: =INDEX(CF_자금판!$E$43:$AH$43,MATCH(DATE(D$5,12,31),CF_자금판!$E$6:$AH$6,0)) -> 9883.1908 | E20: =INDEX(CF_자금판!$E$43:$AH$43,MATCH(DATE(E$5,12,31),CF_자금판!$E$6:$AH$6,0)) -> 9610.5252 | F20: =E20 -> 9610.5252
B21: 기말 인출잔액 | C21: =INDEX(CF_자금판!$E$42:$AH$42,MATCH(DATE(C$5,12,31),CF_자금판!$E$6:$AH$6,0)) -> 0 | D21: =INDEX(CF_자금판!$E$42:$AH$42,MATCH(DATE(D$5,12,31),CF_자금판!$E$6:$AH$6,0)) -> 0 | E21: =INDEX(CF_자금판!$E$42:$AH$42,MATCH(DATE(E$5,12,31),CF_자금판!$E$6:$AH$6,0)) -> 0 | F21: =E21 -> 0
B22: 기간 최저 유동성 | C22: =_xlfn.MINIFS(CF_자금판!$E$43:$AH$43,CF_자금판!$E$6:$AH$6,">="&DATE(C$5,1,1),CF_자금판!$E$6:$AH$6,"<="&DATE(C$5,12,31)) -> 13257.046 | D22: =_xlfn.MINIFS(CF_자금판!$E$43:$AH$43,CF_자금판!$E$6:$AH$6,">="&DATE(D$5,1,1),CF_자금판!$E$6:$AH$6,"<="&DATE(D$5,12,31)) -> 9353.9839 | E22: =_xlfn.MINIFS(CF_자금판!$E$43:$AH$43,CF_자금판!$E$6:$AH$6,">="&DATE(E$5,1,1),CF_자금판!$E$6:$AH$6,"<="&DATE(E$5,12,31)) -> 8923.1058 | F22: =MIN(C22:E22) -> 8923.1058
B24: [2] 회수지연
B25: 항목 | C25: 2026H2 | D25: 2027 | E25: 2028 | F25: 합계 | G25: 비고
B26: 조정 영업 CF | C26: =SUMPRODUCT((YEAR(CF_자금판!$E$6:$AH$6)=C$5)*CF_자금판!$E$51:$AH$51) -> 1508.2868 | D26: =SUMPRODUCT((YEAR(CF_자금판!$E$6:$AH$6)=D$5)*CF_자금판!$E$51:$AH$51) -> 2681.3987 | E26: =SUMPRODUCT((YEAR(CF_자금판!$E$6:$AH$6)=E$5)*CF_자금판!$E$51:$AH$51) -> 3351.7484 | F26: =SUM(C26:E26) -> 7541.4339
B27: 운전자본 증감 | C27: =SUMPRODUCT((YEAR(CF_자금판!$E$6:$AH$6)=C$5)*CF_자금판!$E$52:$AH$52) -> -1492.951 | D27: =SUMPRODUCT((YEAR(CF_자금판!$E$6:$AH$6)=D$5)*CF_자금판!$E$52:$AH$52) -> -2985.9019 | E27: =SUMPRODUCT((YEAR(CF_자금판!$E$6:$AH$6)=E$5)*CF_자금판!$E$52:$AH$52) -> 4478.8529 | F27: =SUM(C27:E27) -> 0 | G27: 회수 지연분 · 정상화 시 환입
B28: GPU 지급 | C28: =SUMPRODUCT((YEAR(CF_자금판!$E$6:$AH$6)=C$5)*CF_자금판!$E$53:$AH$53) -> -839.08 | D28: =SUMPRODUCT((YEAR(CF_자금판!$E$6:$AH$6)=D$5)*CF_자금판!$E$53:$AH$53) -> -3356.32 | E28: =SUMPRODUCT((YEAR(CF_자금판!$E$6:$AH$6)=E$5)*CF_자금판!$E$53:$AH$53) -> 0 | F28: =SUM(C28:E28) -> -4195.4
B29: 기존 CAPEX · 리스원금 | C29: =(SUMPRODUCT((YEAR(CF_자금판!$E$6:$AH$6)=C$5)*CF_자금판!$E$12:$AH$12)+SUMPRODUCT((YEAR(CF_자금판!$E$6:$AH$6)=C$5)*CF_자금판!$E$13:$AH$13)) -> -611.78935 | D29: =(SUMPRODUCT((YEAR(CF_자금판!$E$6:$AH$6)=D$5)*CF_자금판!$E$12:$AH$12)+SUMPRODUCT((YEAR(CF_자금판!$E$6:$AH$6)=D$5)*CF_자금판!$E$13:$AH$13)) -> -1223.5787 | E29: =(SUMPRODUCT((YEAR(CF_자금판!$E$6:$AH$6)=E$5)*CF_자금판!$E$12:$AH$12)+SUMPRODUCT((YEAR(CF_자금판!$E$6:$AH$6)=E$5)*CF_자금판!$E$13:$AH$13)) -> -1223.5787 | F29: =SUM(C29:E29) -> -3058.9468
B30: 배당금 | C30: =SUMPRODUCT((YEAR(CF_자금판!$E$6:$AH$6)=C$5)*CF_자금판!$E$14:$AH$14) -> -726.64461 | D30: =SUMPRODUCT((YEAR(CF_자금판!$E$6:$AH$6)=D$5)*CF_자금판!$E$14:$AH$14) -> -1792.39 | E30: =SUMPRODUCT((YEAR(CF_자금판!$E$6:$AH$6)=E$5)*CF_자금판!$E$14:$AH$14) -> -1792.39 | F30: =SUM(C30:E30) -> -4311.4247 | G30: 4월 기말 · 9월 중간
B31: 기존 사채 상환 | C31: =SUMPRODUCT((YEAR(CF_자금판!$E$6:$AH$6)=C$5)*CF_자금판!$E$15:$AH$15) -> 0 | D31: =SUMPRODUCT((YEAR(CF_자금판!$E$6:$AH$6)=D$5)*CF_자금판!$E$15:$AH$15) -> -1000 | E31: =SUMPRODUCT((YEAR(CF_자금판!$E$6:$AH$6)=E$5)*CF_자금판!$E$15:$AH$15) -> -600 | F31: =SUM(C31:E31) -> -1600
B32: 추가투자 · GPU 추가CF | C32: =SUMPRODUCT((YEAR(CF_자금판!$E$6:$AH$6)=C$5)*CF_자금판!$E$17:$AH$17)-SUMPRODUCT((YEAR(CF_자금판!$E$6:$AH$6)=C$5)*CF_자금판!$E$16:$AH$16) -> 0 | D32: =SUMPRODUCT((YEAR(CF_자금판!$E$6:$AH$6)=D$5)*CF_자금판!$E$17:$AH$17)-SUMPRODUCT((YEAR(CF_자금판!$E$6:$AH$6)=D$5)*CF_자금판!$E$16:$AH$16) -> 0 | E32: =SUMPRODUCT((YEAR(CF_자금판!$E$6:$AH$6)=E$5)*CF_자금판!$E$17:$AH$17)-SUMPRODUCT((YEAR(CF_자금판!$E$6:$AH$6)=E$5)*CF_자금판!$E$16:$AH$16) -> 0 | F32: =SUM(C32:E32) -> 0 | G32: 기본 0
B33: 조달 전 순현금흐름 | C33: =SUMPRODUCT((YEAR(CF_자금판!$E$6:$AH$6)=C$5)*CF_자금판!$E$55:$AH$55) -> -2162.1781 | D33: =SUMPRODUCT((YEAR(CF_자금판!$E$6:$AH$6)=D$5)*CF_자금판!$E$55:$AH$55) -> -7676.7919 | E33: =SUMPRODUCT((YEAR(CF_자금판!$E$6:$AH$6)=E$5)*CF_자금판!$E$55:$AH$55) -> 4214.6326 | F33: =SUM(C33:E33) -> -5624.3375
B34: 신규 인출 | C34: =SUMPRODUCT((YEAR(CF_자금판!$E$6:$AH$6)=C$5)*CF_자금판!$E$62:$AH$62) -> 0 | D34: =SUMPRODUCT((YEAR(CF_자금판!$E$6:$AH$6)=D$5)*CF_자금판!$E$62:$AH$62) -> 4050.2229 | E34: =SUMPRODUCT((YEAR(CF_자금판!$E$6:$AH$6)=E$5)*CF_자금판!$E$62:$AH$62) -> 147.75571 | F34: =SUM(C34:E34) -> 4197.9787
B35: 차입 상환 | C35: =-(SUMPRODUCT((YEAR(CF_자금판!$E$6:$AH$6)=C$5)*CF_자금판!$E$65:$AH$65)) -> 0 | D35: =-(SUMPRODUCT((YEAR(CF_자금판!$E$6:$AH$6)=D$5)*CF_자금판!$E$65:$AH$65)) -> -542.94331 | E35: =-(SUMPRODUCT((YEAR(CF_자금판!$E$6:$AH$6)=E$5)*CF_자금판!$E$65:$AH$65)) -> -3655.0353 | F35: =SUM(C35:E35) -> -4197.9787
B36: 금융비용 | C36: =-(SUMPRODUCT((YEAR(CF_자금판!$E$6:$AH$6)=C$5)*CF_자금판!$E$69:$AH$69)) -> -9.5856164 | D36: =-(SUMPRODUCT((YEAR(CF_자금판!$E$6:$AH$6)=D$5)*CF_자금판!$E$69:$AH$69)) -> -97.739554 | E36: =-(SUMPRODUCT((YEAR(CF_자금판!$E$6:$AH$6)=E$5)*CF_자금판!$E$69:$AH$69)) -> -45.909554 | F36: =SUM(C36:E36) -> -153.23472 | G36: 약정·미사용 수수료 + 이자
B37: 기말 가용유동성 | C37: =INDEX(CF_자금판!$E$67:$AH$67,MATCH(DATE(C$5,12,31),CF_자금판!$E$6:$AH$6,0)) -> 11873.043 | D37: =INDEX(CF_자금판!$E$67:$AH$67,MATCH(DATE(D$5,12,31),CF_자금판!$E$6:$AH$6,0)) -> 7605.7909 | E37: =INDEX(CF_자금판!$E$67:$AH$67,MATCH(DATE(E$5,12,31),CF_자금판!$E$6:$AH$6,0)) -> 8267.2342 | F37: =E37 -> 8267.2342
B38: 기말 인출잔액 | C38: =INDEX(CF_자금판!$E$66:$AH$66,MATCH(DATE(C$5,12,31),CF_자금판!$E$6:$AH$6,0)) -> 0 | D38: =INDEX(CF_자금판!$E$66:$AH$66,MATCH(DATE(D$5,12,31),CF_자금판!$E$6:$AH$6,0)) -> 3507.2796 | E38: =INDEX(CF_자금판!$E$66:$AH$66,MATCH(DATE(E$5,12,31),CF_자금판!$E$6:$AH$6,0)) -> 0 | F38: =E38 -> 0
B39: 기간 최저 유동성 | C39: =_xlfn.MINIFS(CF_자금판!$E$67:$AH$67,CF_자금판!$E$6:$AH$6,">="&DATE(C$5,1,1),CF_자금판!$E$6:$AH$6,"<="&DATE(C$5,12,31)) -> 11873.043 | D39: =_xlfn.MINIFS(CF_자금판!$E$67:$AH$67,CF_자금판!$E$6:$AH$6,">="&DATE(D$5,1,1),CF_자금판!$E$6:$AH$6,"<="&DATE(D$5,12,31)) -> 7605.7909 | E39: =_xlfn.MINIFS(CF_자금판!$E$67:$AH$67,CF_자금판!$E$6:$AH$6,">="&DATE(E$5,1,1),CF_자금판!$E$6:$AH$6,"<="&DATE(E$5,12,31)) -> 7605.7909 | F39: =MIN(C39:E39) -> 7605.7909
B41: [3] 복합위기
B42: 항목 | C42: 2026H2 | D42: 2027 | E42: 2028 | F42: 합계 | G42: 비고
B43: 조정 영업 CF | C43: =SUMPRODUCT((YEAR(CF_자금판!$E$6:$AH$6)=C$5)*CF_자금판!$E$75:$AH$75) -> 1340.6994 | D43: =SUMPRODUCT((YEAR(CF_자금판!$E$6:$AH$6)=D$5)*CF_자금판!$E$75:$AH$75) -> 2011.0491 | E43: =SUMPRODUCT((YEAR(CF_자금판!$E$6:$AH$6)=E$5)*CF_자금판!$E$75:$AH$75) -> 2011.0491 | F43: =SUM(C43:E43) -> 5362.7975
B44: 운전자본 증감 | C44: =SUMPRODUCT((YEAR(CF_자금판!$E$6:$AH$6)=C$5)*CF_자금판!$E$76:$AH$76) -> -2985.9019 | D44: =SUMPRODUCT((YEAR(CF_자금판!$E$6:$AH$6)=D$5)*CF_자금판!$E$76:$AH$76) -> -5971.8038 | E44: =SUMPRODUCT((YEAR(CF_자금판!$E$6:$AH$6)=E$5)*CF_자금판!$E$76:$AH$76) -> 0 | F44: =SUM(C44:E44) -> -8957.7058 | G44: 회수 지연분 · 정상화 시 환입
B45: GPU 지급 | C45: =SUMPRODUCT((YEAR(CF_자금판!$E$6:$AH$6)=C$5)*CF_자금판!$E$77:$AH$77) -> -915.36 | D45: =SUMPRODUCT((YEAR(CF_자금판!$E$6:$AH$6)=D$5)*CF_자금판!$E$77:$AH$77) -> -3661.44 | E45: =SUMPRODUCT((YEAR(CF_자금판!$E$6:$AH$6)=E$5)*CF_자금판!$E$77:$AH$77) -> 0 | F45: =SUM(C45:E45) -> -4576.8
B46: 기존 CAPEX · 리스원금 | C46: =(SUMPRODUCT((YEAR(CF_자금판!$E$6:$AH$6)=C$5)*CF_자금판!$E$12:$AH$12)+SUMPRODUCT((YEAR(CF_자금판!$E$6:$AH$6)=C$5)*CF_자금판!$E$13:$AH$13)) -> -611.78935 | D46: =(SUMPRODUCT((YEAR(CF_자금판!$E$6:$AH$6)=D$5)*CF_자금판!$E$12:$AH$12)+SUMPRODUCT((YEAR(CF_자금판!$E$6:$AH$6)=D$5)*CF_자금판!$E$13:$AH$13)) -> -1223.5787 | E46: =(SUMPRODUCT((YEAR(CF_자금판!$E$6:$AH$6)=E$5)*CF_자금판!$E$12:$AH$12)+SUMPRODUCT((YEAR(CF_자금판!$E$6:$AH$6)=E$5)*CF_자금판!$E$13:$AH$13)) -> -1223.5787 | F46: =SUM(C46:E46) -> -3058.9468
B47: 배당금 | C47: =SUMPRODUCT((YEAR(CF_자금판!$E$6:$AH$6)=C$5)*CF_자금판!$E$14:$AH$14) -> -726.64461 | D47: =SUMPRODUCT((YEAR(CF_자금판!$E$6:$AH$6)=D$5)*CF_자금판!$E$14:$AH$14) -> -1792.39 | E47: =SUMPRODUCT((YEAR(CF_자금판!$E$6:$AH$6)=E$5)*CF_자금판!$E$14:$AH$14) -> -1792.39 | F47: =SUM(C47:E47) -> -4311.4247 | G47: 4월 기말 · 9월 중간
B48: 기존 사채 상환 | C48: =SUMPRODUCT((YEAR(CF_자금판!$E$6:$AH$6)=C$5)*CF_자금판!$E$15:$AH$15) -> 0 | D48: =SUMPRODUCT((YEAR(CF_자금판!$E$6:$AH$6)=D$5)*CF_자금판!$E$15:$AH$15) -> -1000 | E48: =SUMPRODUCT((YEAR(CF_자금판!$E$6:$AH$6)=E$5)*CF_자금판!$E$15:$AH$15) -> -600 | F48: =SUM(C48:E48) -> -1600
B49: 추가투자 · GPU 추가CF | C49: =SUMPRODUCT((YEAR(CF_자금판!$E$6:$AH$6)=C$5)*CF_자금판!$E$17:$AH$17)-SUMPRODUCT((YEAR(CF_자금판!$E$6:$AH$6)=C$5)*CF_자금판!$E$16:$AH$16) -> 0 | D49: =SUMPRODUCT((YEAR(CF_자금판!$E$6:$AH$6)=D$5)*CF_자금판!$E$17:$AH$17)-SUMPRODUCT((YEAR(CF_자금판!$E$6:$AH$6)=D$5)*CF_자금판!$E$16:$AH$16) -> 0 | E49: =SUMPRODUCT((YEAR(CF_자금판!$E$6:$AH$6)=E$5)*CF_자금판!$E$17:$AH$17)-SUMPRODUCT((YEAR(CF_자금판!$E$6:$AH$6)=E$5)*CF_자금판!$E$16:$AH$16) -> 0 | F49: =SUM(C49:E49) -> 0 | G49: 기본 0
B50: 조달 전 순현금흐름 | C50: =SUMPRODUCT((YEAR(CF_자금판!$E$6:$AH$6)=C$5)*CF_자금판!$E$79:$AH$79) -> -3898.9965 | D50: =SUMPRODUCT((YEAR(CF_자금판!$E$6:$AH$6)=D$5)*CF_자금판!$E$79:$AH$79) -> -11638.164 | E50: =SUMPRODUCT((YEAR(CF_자금판!$E$6:$AH$6)=E$5)*CF_자금판!$E$79:$AH$79) -> -1604.9197 | F50: =SUM(C50:E50) -> -17142.08
B51: 신규 인출 | C51: =SUMPRODUCT((YEAR(CF_자금판!$E$6:$AH$6)=C$5)*CF_자금판!$E$86:$AH$86) -> 0 | D51: =SUMPRODUCT((YEAR(CF_자금판!$E$6:$AH$6)=D$5)*CF_자금판!$E$86:$AH$86) -> 4500 | E51: =SUMPRODUCT((YEAR(CF_자금판!$E$6:$AH$6)=E$5)*CF_자금판!$E$86:$AH$86) -> 0 | F51: =SUM(C51:E51) -> 4500
B52: 차입 상환 | C52: =-(SUMPRODUCT((YEAR(CF_자금판!$E$6:$AH$6)=C$5)*CF_자금판!$E$89:$AH$89)) -> 0 | D52: =-(SUMPRODUCT((YEAR(CF_자금판!$E$6:$AH$6)=D$5)*CF_자금판!$E$89:$AH$89)) -> 0 | E52: =-(SUMPRODUCT((YEAR(CF_자금판!$E$6:$AH$6)=E$5)*CF_자금판!$E$89:$AH$89)) -> -4500 | F52: =SUM(C52:E52) -> -4500
B53: 금융비용 | C53: =-(SUMPRODUCT((YEAR(CF_자금판!$E$6:$AH$6)=C$5)*CF_자금판!$E$93:$AH$93)) -> -9.5856164 | D53: =-(SUMPRODUCT((YEAR(CF_자금판!$E$6:$AH$6)=D$5)*CF_자금판!$E$93:$AH$93)) -> -147.90709 | E53: =-(SUMPRODUCT((YEAR(CF_자금판!$E$6:$AH$6)=E$5)*CF_자금판!$E$93:$AH$93)) -> -141.87945 | F53: =SUM(C53:E53) -> -299.37215 | G53: 약정·미사용 수수료 + 이자
B54: 기말 가용유동성 | C54: =INDEX(CF_자금판!$E$91:$AH$91,MATCH(DATE(C$5,12,31),CF_자금판!$E$6:$AH$6,0)) -> 10136.224 | D54: =INDEX(CF_자금판!$E$91:$AH$91,MATCH(DATE(D$5,12,31),CF_자금판!$E$6:$AH$6,0)) -> 2850.1537 | E54: =INDEX(CF_자금판!$E$91:$AH$91,MATCH(DATE(E$5,12,31),CF_자금판!$E$6:$AH$6,0)) -> -3396.6454 | F54: =E54 -> -3396.6454
B55: 기말 인출잔액 | C55: =INDEX(CF_자금판!$E$90:$AH$90,MATCH(DATE(C$5,12,31),CF_자금판!$E$6:$AH$6,0)) -> 0 | D55: =INDEX(CF_자금판!$E$90:$AH$90,MATCH(DATE(D$5,12,31),CF_자금판!$E$6:$AH$6,0)) -> 4500 | E55: =INDEX(CF_자금판!$E$90:$AH$90,MATCH(DATE(E$5,12,31),CF_자금판!$E$6:$AH$6,0)) -> 0 | F55: =E55 -> 0
B56: 기간 최저 유동성 | C56: =_xlfn.MINIFS(CF_자금판!$E$91:$AH$91,CF_자금판!$E$6:$AH$6,">="&DATE(C$5,1,1),CF_자금판!$E$6:$AH$6,"<="&DATE(C$5,12,31)) -> 10136.224 | D56: =_xlfn.MINIFS(CF_자금판!$E$91:$AH$91,CF_자금판!$E$6:$AH$6,">="&DATE(D$5,1,1),CF_자금판!$E$6:$AH$6,"<="&DATE(D$5,12,31)) -> 2700.9245 | E56: =_xlfn.MINIFS(CF_자금판!$E$91:$AH$91,CF_자금판!$E$6:$AH$6,">="&DATE(E$5,1,1),CF_자금판!$E$6:$AH$6,"<="&DATE(E$5,12,31)) -> -3593.513 | F56: =MIN(C56:E56) -> -3593.513

Sheet 공시원문
B2: LG CNS 자금판 — 공시원문 (원문 단위 보존)
B3: 원문 금액·단위 그대로 입력 · F열 억원 환산 · 분석 기준 2026.10 · 이후 공시 미반영 · 노란 음영 = 입력값
B5: [1] 공시 금액
B6: 항목 | C6: 원문 금액 | D6: 단위 | E6: 원/단위 | F6: 억원 | G6: 출처 | H6: 공시 위치 | I6: 기준
B7: 2025말 별도 현금 | C7: 976730662 | D7: 천원 | E7: 1000 | F7: =C7*E7/100000000 -> 9767.3066 | G7: S1 | H7: 4-4 현금흐름표 | I7: 2025.12 말
B8: 2026H1말 별도 현금 | C8: 404480644 | D8: 천원 | E8: 1000 | F8: =C8*E8/100000000 -> 4044.8064 | G8: S1 | H8: 4-1 재무상태표 | I8: 2026.06 말
B9: 2025말 별도 유동 예치금 | C9: 500000000 | D9: 천원 | E9: 1000 | F9: =C9*E9/100000000 -> 5000 | G9: S1 | H9: 4-1 재무상태표 | I9: 2025.12 말
B10: 2026H1말 별도 유동 예치금 | C10: 1000000000 | D10: 천원 | E10: 1000 | F10: =C10*E10/100000000 -> 10000 | G10: S1 | H10: 4-1 재무상태표 | I10: 2026.06 말
B11: 2026H1 별도 영업현금흐름 | C11: 344971580 | D11: 천원 | E11: 1000 | F11: =C11*E11/100000000 -> 3449.7158 | G11: S1 | H11: 4-4 현금흐름표 | I11: 2026 상반기
B12: 2026H1 별도 투자현금흐름 | C12: -533713316 | D12: 천원 | E12: 1000 | F12: =C12*E12/100000000 -> -5337.1332 | G12: S1 | H12: 4-4 현금흐름표 | I12: 2026 상반기
B13: 2026H1 별도 재무현금흐름 | C13: -383925869 | D13: 천원 | E13: 1000 | F13: =C13*E13/100000000 -> -3839.2587 | G13: S1 | H13: 4-4 현금흐름표 | I13: 2026 상반기
B14: 2026H1 별도 현금 환율효과 | C14: 417587 | D14: 천원 | E14: 1000 | F14: =C14*E14/100000000 -> 4.17587 | G14: S1 | H14: 4-4 현금흐름표 | I14: 2026 상반기
B15: 2026H1 예치금 순증가 | C15: 500000000 | D15: 천원 | E15: 1000 | F15: =C15*E15/100000000 -> 5000 | G15: S1 | H15: 유입 400,000,000 / 유출 900,000,000 | I15: 2026 상반기
B16: 2026H1 사채 상환 | C16: 230000000 | D16: 천원 | E16: 1000 | F16: =C16*E16/100000000 -> 2300 | G16: S1 | H16: 4-4 현금흐름표 | I16: 2026 상반기
B17: 2026H1 리스원금 상환 | C17: 47351326 | D17: 천원 | E17: 1000 | F17: =C17*E17/100000000 -> 473.51326 | G17: S1 | H17: 4-4 현금흐름표 | I17: 2026 상반기
B18: 2026H1 배당금 지급 | C18: 106574543 | D18: 천원 | E18: 1000 | F18: =C18*E18/100000000 -> 1065.7454 | G18: S1 | H18: 4-4 현금흐름표 | I18: 2026 상반기
... B41: 2026H1 별도 자본총계 | C41: 2701074819 | D41: 천원 | E41: 1000 | F41: =C41*E41/100000000 -> 27010.748 | G41: S1 | H41: 4-1 재무상태표 | I41: 2026.06 말
B43: [2] 출처
B44: 코드 | C44: 자료 | F44: 공시일 | H44: 링크
B45: S1 | C45: 2026년 반기보고서 | F45: 2026.08.14 | H45: https://dart.fss.or.kr/dsaf001/main.do?rcpNo=20260814002448
B46: S2 | C46: 유형자산 취득결정 (GPU·인프라 장비) | F46: 2026.09.11 | H46: https://dart.fss.or.kr/dsaf001/main.do?rcpNo=20260911800638
B47: S3 | C47: 현금·현물배당 결정 (중간배당) | F47: 2026.08.05 | H47: https://financialfilings.com/filings/lg-cns-co-ltd/notice-of-dividend-amount/2026/49961973/
B48: S4 | C48: 2026년 2분기 경영실적 (IR) | F48: 2026.07 | H48: https://www.lgcns.com/content/dam/lgcns/resources/company/ir/investors-activity/earnings-announcement/LG%20CNS_2Q26_Earnings_KR.pdf
B49: S5 | C49: 상반기 실적 보도자료 | F49: 2026.07 | H49: https://connect.lgcns.com/kr/newsroom/press/detail.ir-2607-3
B50: S6 | C50: General Atlantic 공동투자 협약 | F50: 2026.10.01 | H50: https://connect.lgcns.com/kr/newsroom/press/detail.ax-2610-1
B51: S7 | C51: IFRS Foundation — IAS 16 / IFRS 16 | F51: 열람 2026.10 | H51: https://www.ifrs.org/issued-standards/list-of-standards/ifrs-16-leases/

Sheet 통제·실행
B2: LG CNS 자금판 — 통제 설계 · 실행 순서
B3: 공개자료 기반 통제 설계 예시 · 실제 통제 결함·미비점 진단과 구분
B5: [1] 투자·조달 수치의 통제 설계
B6: 대상 | C6: 위험 | D6: 책임 / 주기 | E6: 통제 | F6: 증빙 | G6: 재무제표 주장
B7: 투자 승인 | C7: 승인 한도 초과 · 중복 발주 | D7: 투자심의 / 발주 전 | E7: 투자 승인번호와 발주·계약 금액 대사 · 변경분 재승인 | F7: 이사회 의사록 · 투자품의 · 변경 승인 | G7: 권한 승인 · 완전성
B8: 지급·선급금 | C8: 허위 계좌 · 중복 지급 · 선급금 미정산 | D8: 구매·자금 / 지급 건별 | E8: 계약·검수·청구서 3자 대사 · 계좌 변경 독립 확인 · 지급자 분리 | F8: 계약 원본 · 검수서 · 은행 확인 · 지급 로그 | G8: 발생 · 정확성
B9: 자산 인식 | C9: 납품 전 본계정 대체 · 비용 자산화 | D9: 재무회계 / 월 결산 | E9: 선급금·건설중자산·장비·용역 구분 · 사용가능일 확인 후 상각 | F9: 구성품 명세 · 인수 테스트 · 가동 승인 | G9: 분류 · 기간귀속
B10: 매출·회수 | C10: 가동률의 매출 간주 · 미수금 누락 | D10: 사업·채권관리 / 월별 | E10: 성과의무·청구조건과 사용량 대사 · 연체·분쟁 별도 검토 | F10: 고객 계약 · 사용 로그 · 청구·수금 대사 | G10: 발생 · 평가
B11: 차입·약정 | C11: 공급자 금융을 가용 한도로 오인 | D11: 자금·재무회계 / 월별 | E11: 은행 확인서로 확약·미사용 한도 확인 · 만기·조건 원장 대사 | F11: 약정 원본 · 은행 확인 · 차입 대장 | G11: 완전성 · 표시
B12: 리스·손상 | C12: 서비스 계약 속 리스 누락 · 잔존가치 과대 | D12: 재무회계 / 계약·분기 | E12: 특정 자산·통제 여부 검토 · 유휴·교체 GPU 손상징후 점검 | F12: 리스 판정 메모 · 이용률 · 수익성 재추정 | G12: 분류 · 평가
B13: 자금 예측 | C13: 가정 변경 미승인 · 예금 가용성 오류 | D13: 자금·검토자 / 주간 | E13: 13주 예측과 은행 잔액·예금 만기 대사 · 버전·변경 승인 · 차이 분석 | F13: 예측 파일 · 수정 로그 · 실적 차이 설명 | G13: 정확성 · 완전성
B15: [2] 실행 순서
B16: 순서 | C16: 작업 | D16: 시점 | E16: 내용 | F16: 산출물
B17: 1 | C17: 실제 잔액 확인 | D17: 착수 1주 | E17: 2026.07 이후 실적 · 은행별 예금 만기·질권 대사 | F17: 기초 유동성 갱신 · 가용 한도
B18: 2 | C18: 계약 현금흐름 | D18: 착수 1주 | E18: GPU 지급·검수·환율·세금 · 거래처별 수금일 확인 | F18: 13주 자금계획 · 월별 지급표
B19: 3 | C19: 스트레스 재계산 | D19: 착수 2주 | E19: 회수 지연·원가 상승·예금 제약 재시험 | F19: 필요 최대 인출 · 하한 · 상환 시점
B20: 4 | C20: 금융기관 협의 | D20: 착수 2–4주 | E20: 기존 한도 차감 후 복수 은행 조건 비교 | F20: 총비용·약정 비교 · 승인안
B21: 5 | C21: 승인·체결 | D21: 착수 5주 | E21: 총 금융비용·약정·상환재원 검토 후 내부 권한 승인 | F21: 약정서 · 승인 기록
B22: 6 | C22: 사후 관리 | D22: 체결 후 매주 | E22: 주별 예측 차이 · 월별 한도 사용·상환 · 약정 준수 | F22: 예외 보고 · 원장 대사
B24: 회수 정상화가 지연되면 만기 6개월 전부터 장기 조달·투자 집행 조정을 함께 검토

Sheet 검증
B2: LG CNS 자금판 — 검증
B3: 수식 검증 = 0이면 정상 · 경제적 경보 = 0 초과 시 자금 대응 필요 (수식 오류 아님)
B5: [1] 수식 검증
B6: 점검 항목 | C6: 결과 | D6: 기준 | E6: 상태 | F6: 설명
B7: 상반기 현금 검산 | C7: =가정!$C$27 -> 0 | D7: 0 | E7: =IF(ABS(C7)<0.01,"정상","확인") -> 정상 | F7: 공시 기말 현금과 계산 일치
B8: GPU 지급비중 합계 − 100% | C8: =CF_자금판!$C$10-1 -> 0 | D8: 0 | E8: =IF(ABS(C8)<0.01,"정상","확인") -> 정상 | F8: 지급 누락·중복 방지
B9: 기본 누적 대사 | C9: =가정!$D$11+CF_자금판!$C$31+CF_자금판!$C$38-CF_자금판!$C$41-CF_자금판!$C$45-CF_자금판!$AH$43 -> 0 | D9: 0 | E9: =IF(ABS(C9)<0.01,"정상","확인") -> 정상 | F9: 기초 + 순CF + 인출 − 상환 − 비용 = 기말
B10: 회수지연 누적 대사 | C10: =가정!$D$11+CF_자금판!$C$55+CF_자금판!$C$62-CF_자금판!$C$65-CF_자금판!$C$69-CF_자금판!$AH$67 -> 0 | D10: 0 | E10: =IF(ABS(C10)<0.01,"정상","확인") -> 정상 | F10: 기초 + 순CF + 인출 − 상환 − 비용 = 기말
B11: 복합위기 누적 대사 | C11: =가정!$D$11+CF_자금판!$C$79+CF_자금판!$C$86-CF_자금판!$C$89-CF_자금판!$C$93-CF_자금판!$AH$91 -> 0 | D11: 0 | E11: =IF(ABS(C11)<0.01,"정상","확인") -> 정상 | F11: 기초 + 순CF + 인출 − 상환 − 비용 = 기말
B12: 한도 초과 인출 | C12: =MAX(0,MAX(CF_자금판!$E$42:$AH$42,CF_자금판!$E$66:$AH$66,CF_자금판!$E$90:$AH$90)-가정!$C$61) -> 0 | D12: 0 | E12: =IF(ABS(C12)<0.01,"정상","확인") -> 정상 | F12: 인출잔액 ≤ 확약한도
B13: 만기 후 잔여 차입 | C13: =SUMPRODUCT((CF_자금판!$E$6:$AH$6>=EOMONTH(가정!$C$70,0))*CF_자금판!$E$42:$AH$42)+SUMPRODUCT((CF_자금판!$E$6:$AH$6>=EOMONTH(가정!$C$70,0))*CF_자금판!$E$66:$AH$66)+SUMPRODUCT((CF_자금판!$E$6:$AH$6>=EOMONTH(가정!$C$70,0))*CF_자금판!$E$90:$AH$90) -> 0 | D13: 0 | E13: =IF(ABS(C13)<0.01,"정상","확인") -> 정상 | F13: 만기월 전액 상환 · 자동 차환 없음
B14: 사채 원금 대사 | C14: =CF_자금판!$C$15+가정!$C$45+가정!$C$46 -> 0 | D14: 0 | E14: =IF(ABS(C14)<0.01,"정상","확인") -> 정상 | F14: 2개 만기 1,600억원
B15: 예금 미가용액 ≤ 유동 예치금 | C15: =MAX(0,가정!$D$10-가정!$D$8) -> 0 | D15: 0 | E15: =IF(ABS(C15)<0.01,"정상","확인") -> 정상
B16: 산정 한도 − 확약한도 | C16: =가정!$C$63-가정!$C$61 -> 0 | D16: 0 | E16: =IF(ABS(C16)<0.01,"정상","확인") -> 정상 | F16: 0이 아니면 한도 재검토
B18: [2] 경제적 경보
B19: 점검 항목 | C19: 결과 | D19: 기준 | E19: 상태 | F19: 설명
B20: 기본 하한 부족 (조달 후) | C20: =MAX(0,-CF_자금판!$D$44) -> 0 | D20: 0 | E20: =IF(C20<0.01,"정상","대응 필요") -> 정상 | F20: 0 초과 = 한도 외 추가 대응 필요 (투자·배당 조정, 장기 조달)
B21: 회수지연 하한 부족 (조달 후) | C21: =MAX(0,-CF_자금판!$D$68) -> 0 | D21: 0 | E21: =IF(C21<0.01,"정상","대응 필요") -> 정상 | F21: 0 초과 = 한도 외 추가 대응 필요 (투자·배당 조정, 장기 조달)
B22: 복합위기 하한 부족 (조달 후) | C22: =MAX(0,-CF_자금판!$D$92) -> 11199.304 | D22: 0 | E22: =IF(C22<0.01,"정상","대응 필요") -> 대응 필요 | F22: 0 초과 = 한도 외 추가 대응 필요 (투자·배당 조정, 장기 조달)
